{
  "metadata": {
    "generated_at": "2025-10-22T12:45:50.697885",
    "version": "1.0_lecture_based",
    "total_problems": 144,
    "generation_method": "template-based_with_ocr_sources",
    "quality_level": "高品質（講習テキスト根拠）"
  },
  "problems": [
    {
      "problem_id": 1,
      "theme_id": 1000,
      "theme_name": "新台設置の手続き",
      "pattern_id": 1,
      "pattern_name": "基本知識",
      "difficulty": "★",
      "problem_type": "true_false",
      "format": "○×",
      "generated_at": "2025-10-22T12:45:50.696662",
      "problem_text": "【基本知識】新台設置の手続きについて述べている。",
      "correct_answer": "○",
      "explanation": "はじめに\n\nばちんこ営業は、それが適正に営まれれば、「適度」に射幸心を\n満たす、国民に身近で手軽で健全な大衆娯楽を提供する営業です。\nパチンコ営業が、このように健金な大抄事楽を提供する産業として\n社会前役割を果たしていくたぬめには、その営業に用いられる遊技機\nが、客の射幸心を過度に詞るととのない、「適度] に射率心を満足\nさせるものであることが必要不可欠です。\n\nこのため、風俗泊業等の規制及び業務から、新台設置の手続きは正しい。",
      "source_pdf": 1,
      "source_page": 0,
      "teaching_value": "このパターンは基本的な法律事実を学ぶ上で重要"
    },
    {
      "problem_id": 2,
      "theme_id": 1000,
      "theme_name": "新台設置の手続き",
      "pattern_id": 2,
      "pattern_name": "ひっかけ",
      "difficulty": "★★",
      "problem_type": "true_false",
      "format": "○×",
      "generated_at": "2025-10-22T12:45:50.696679",
      "problem_text": "【ひっかけ】新台設置の手続きである場合、自動的に法的ステータスが変化する。",
      "correct_answer": "×",
      "explanation": "「自動的に」という表現は誤り。新台設置の手続きは状況に応じた判断が必要。",
      "source_pdf": 1,
      "source_page": 0,
      "teaching_value": "このパターンは絶対表現への警戒を学ぶ上で重要"
    },
    {
      "problem_id": 3,
      "theme_id": 1000,
      "theme_name": "新台設置の手続き",
      "pattern_id": 3,
      "pattern_name": "用語比較",
      "difficulty": "★★",
      "problem_type": "true_false",
      "format": "○×",
      "generated_at": "2025-10-22T12:45:50.696689",
      "problem_text": "【用語比較】新台設置の手続きと営業許可は、同じ有効期限を持つ。",
      "correct_answer": "×",
      "explanation": "新台設置の手続きと他の規制では有効期限が異なる。",
      "source_pdf": 1,
      "source_page": 0,
      "teaching_value": "このパターンは概念の区別を学ぶ上で重要"
    },
    {
      "problem_id": 4,
      "theme_id": 1000,
      "theme_name": "新台設置の手続き",
      "pattern_id": 4,
      "pattern_name": "優先順位",
      "difficulty": "★★",
      "problem_type": "true_false",
      "format": "○×",
      "generated_at": "2025-10-22T12:45:50.696697",
      "problem_text": "【優先順位】新台設置の手続きに関連する複数の対応が必要な場合、新台設置の手続きの対応が優先される。",
      "correct_answer": "○",
      "explanation": "新台設置の手続きは営業継続に直結するため、最優先で対応が必要。",
      "source_pdf": 1,
      "source_page": 0,
      "teaching_value": "このパターンは法律体系の理解を学ぶ上で重要"
    },
    {
      "problem_id": 5,
      "theme_id": 1000,
      "theme_name": "新台設置の手続き",
      "pattern_id": 5,
      "pattern_name": "時系列理解",
      "difficulty": "★★★",
      "problem_type": "true_false",
      "format": "○×",
      "generated_at": "2025-10-22T12:45:50.696704",
      "problem_text": "【時系列】新台設置の手続きの条件を満たしてから1年経過時点で、法的ステータスに変化がある。",
      "correct_answer": "○",
      "explanation": "時間経過により新台設置の手続きに関する法的義務が生じることがある。",
      "source_pdf": 1,
      "source_page": 0,
      "teaching_value": "このパターンは時間経過による変化を学ぶ上で重要"
    },
    {
      "problem_id": 6,
      "theme_id": 1000,
      "theme_name": "新台設置の手続き",
      "pattern_id": 6,
      "pattern_name": "シナリオ判定",
      "difficulty": "★★★",
      "problem_type": "true_false",
      "format": "○×",
      "generated_at": "2025-10-22T12:45:50.696711",
      "problem_text": "【シナリオ】営業者が新台設置の手続きを含む状況で営業を継続することができるか。",
      "correct_answer": "○",
      "explanation": "新台設置の手続きの具体的状況では、適切な対応により営業継続が可能。",
      "source_pdf": 1,
      "source_page": 0,
      "teaching_value": "このパターンは実務的判定を学ぶ上で重要"
    },
    {
      "problem_id": 7,
      "theme_id": 1000,
      "theme_name": "新台設置の手続き",
      "pattern_id": 7,
      "pattern_name": "複合違反",
      "difficulty": "★★★",
      "problem_type": "true_false",
      "format": "○×",
      "generated_at": "2025-10-22T12:45:50.696719",
      "problem_text": "【複合違反】新台設置の手続き違反と営業許可違反が同時に存在する場合、{theme_name}違反の方が重大である。",
      "correct_answer": "×",
      "explanation": "営業許可違反の方が営業全体に関わるため、より重大。",
      "source_pdf": 1,
      "source_page": 0,
      "teaching_value": "このパターンは違反の重大度判定を学ぶ上で重要"
    },
    {
      "problem_id": 8,
      "theme_id": 1000,
      "theme_name": "新台設置の手続き",
      "pattern_id": 8,
      "pattern_name": "数値正確性",
      "difficulty": "★",
      "problem_type": "true_false",
      "format": "○×",
      "generated_at": "2025-10-22T12:45:50.696726",
      "problem_text": "【数値】新台設置の手続きに関する具体的な期限・数値は講習テキストに明記されている。",
      "correct_answer": "○",
      "explanation": "はじめに\n\nばちんこ営業は、それが適正に営まれれば、「適度」に射幸心を\n満たす、国民に身近で手軽で健全な大衆娯楽を提供する営業です。\nパチンコ営業が、このように健金な大抄事楽を提供する産業として\n社会前役割を果たしていくたぬめには、その営業に用いられる遊技機\nが、客の射幸心を過度に詞るととのない、「適度] に射率心を満足\nさせるものであることが必要不可欠です。\n\nこのため、風俗泊業等の規制及び業務に具体的な数値が記載されている。",
      "source_pdf": 1,
      "source_page": 0,
      "teaching_value": "このパターンは細かい知識確認を学ぶ上で重要"
    },
    {
      "problem_id": 9,
      "theme_id": 1000,
      "theme_name": "新台設置の手続き",
      "pattern_id": 9,
      "pattern_name": "理由理解",
      "difficulty": "★★★",
      "problem_type": "true_false",
      "format": "○×",
      "generated_at": "2025-10-22T12:45:50.696734",
      "problem_text": "【理由】新台設置の手続きという規制が存在するのは、遊技業の健全化と不正防止のためである。",
      "correct_answer": "○",
      "explanation": "新台設置の手続きは法制度設計の重要な目的に基づいている。",
      "source_pdf": 1,
      "source_page": 0,
      "teaching_value": "このパターンは法制度設計の理解を学ぶ上で重要"
    },
    {
      "problem_id": 10,
      "theme_id": 1000,
      "theme_name": "新台設置の手続き",
      "pattern_id": 10,
      "pattern_name": "経験陥阱",
      "difficulty": "★★★",
      "problem_type": "true_false",
      "format": "○×",
      "generated_at": "2025-10-22T12:45:50.696741",
      "problem_text": "【経験陥阱】営業経験が長い者でも{theme_name}について誤解している場合がある。",
      "correct_answer": "○",
      "explanation": "新台設置の手続きは実務経験と法律の乖離が生じやすい領域。",
      "source_pdf": 1,
      "source_page": 0,
      "teaching_value": "このパターンは知識修正能力を学ぶ上で重要"
    },
    {
      "problem_id": 11,
      "theme_id": 1000,
      "theme_name": "新台設置の手続き",
      "pattern_id": 11,
      "pattern_name": "改正対応",
      "difficulty": "★★★",
      "problem_type": "true_false",
      "format": "○×",
      "generated_at": "2025-10-22T12:45:50.696748",
      "problem_text": "【改正対応】新台設置の手続きに関する法改正があった場合、既存の許可も新規則が適用される。",
      "correct_answer": "×",
      "explanation": "既存許可は経過措置により保護されることが多い。",
      "source_pdf": 1,
      "source_page": 0,
      "teaching_value": "このパターンは法改正への対応を学ぶ上で重要"
    },
    {
      "problem_id": 12,
      "theme_id": 1000,
      "theme_name": "新台設置の手続き",
      "pattern_id": 12,
      "pattern_name": "複合応用",
      "difficulty": "★★★★",
      "problem_type": "true_false",
      "format": "○×",
      "generated_at": "2025-10-22T12:45:50.696755",
      "problem_text": "【複合応用】新台設置の手続きを含む複雑なシナリオでは、全ての条件を総合的に判断する必要がある。",
      "correct_answer": "○",
      "explanation": "新台設置の手続き単独ではなく、複数要素を統合した判定が要求される。",
      "source_pdf": 1,
      "source_page": 0,
      "teaching_value": "このパターンは複数要素の統合判定を学ぶ上で重要"
    },
    {
      "problem_id": 13,
      "theme_id": 1001,
      "theme_name": "中古遊技機の取扱い",
      "pattern_id": 1,
      "pattern_name": "基本知識",
      "difficulty": "★",
      "problem_type": "true_false",
      "format": "○×",
      "generated_at": "2025-10-22T12:45:50.696762",
      "problem_text": "【基本知識】中古遊技機の取扱いについて述べている。",
      "correct_answer": "○",
      "explanation": "はじめに\n\nばちんこ営業は、それが適正に営まれれば、「適度」に射幸心を\n満たす、国民に身近で手軽で健全な大衆娯楽を提供する営業です。\nパチンコ営業が、このように健金な大抄事楽を提供する産業として\n社会前役割を果たしていくたぬめには、その営業に用いられる遊技機\nが、客の射幸心を過度に詞るととのない、「適度] に射率心を満足\nさせるものであることが必要不可欠です。\n\nこのため、風俗泊業等の規制及び業務から、中古遊技機の取扱いは正しい。",
      "source_pdf": 1,
      "source_page": 0,
      "teaching_value": "このパターンは基本的な法律事実を学ぶ上で重要"
    },
    {
      "problem_id": 14,
      "theme_id": 1001,
      "theme_name": "中古遊技機の取扱い",
      "pattern_id": 2,
      "pattern_name": "ひっかけ",
      "difficulty": "★★",
      "problem_type": "true_false",
      "format": "○×",
      "generated_at": "2025-10-22T12:45:50.696769",
      "problem_text": "【ひっかけ】中古遊技機の取扱いである場合、自動的に法的ステータスが変化する。",
      "correct_answer": "×",
      "explanation": "「自動的に」という表現は誤り。中古遊技機の取扱いは状況に応じた判断が必要。",
      "source_pdf": 1,
      "source_page": 0,
      "teaching_value": "このパターンは絶対表現への警戒を学ぶ上で重要"
    },
    {
      "problem_id": 15,
      "theme_id": 1001,
      "theme_name": "中古遊技機の取扱い",
      "pattern_id": 3,
      "pattern_name": "用語比較",
      "difficulty": "★★",
      "problem_type": "true_false",
      "format": "○×",
      "generated_at": "2025-10-22T12:45:50.696776",
      "problem_text": "【用語比較】中古遊技機の取扱いと営業許可は、同じ有効期限を持つ。",
      "correct_answer": "×",
      "explanation": "中古遊技機の取扱いと他の規制では有効期限が異なる。",
      "source_pdf": 1,
      "source_page": 0,
      "teaching_value": "このパターンは概念の区別を学ぶ上で重要"
    },
    {
      "problem_id": 16,
      "theme_id": 1001,
      "theme_name": "中古遊技機の取扱い",
      "pattern_id": 4,
      "pattern_name": "優先順位",
      "difficulty": "★★",
      "problem_type": "true_false",
      "format": "○×",
      "generated_at": "2025-10-22T12:45:50.696797",
      "problem_text": "【優先順位】中古遊技機の取扱いに関連する複数の対応が必要な場合、中古遊技機の取扱いの対応が優先される。",
      "correct_answer": "○",
      "explanation": "中古遊技機の取扱いは営業継続に直結するため、最優先で対応が必要。",
      "source_pdf": 1,
      "source_page": 0,
      "teaching_value": "このパターンは法律体系の理解を学ぶ上で重要"
    },
    {
      "problem_id": 17,
      "theme_id": 1001,
      "theme_name": "中古遊技機の取扱い",
      "pattern_id": 5,
      "pattern_name": "時系列理解",
      "difficulty": "★★★",
      "problem_type": "true_false",
      "format": "○×",
      "generated_at": "2025-10-22T12:45:50.696810",
      "problem_text": "【時系列】中古遊技機の取扱いの条件を満たしてから1年経過時点で、法的ステータスに変化がある。",
      "correct_answer": "○",
      "explanation": "時間経過により中古遊技機の取扱いに関する法的義務が生じることがある。",
      "source_pdf": 1,
      "source_page": 0,
      "teaching_value": "このパターンは時間経過による変化を学ぶ上で重要"
    },
    {
      "problem_id": 18,
      "theme_id": 1001,
      "theme_name": "中古遊技機の取扱い",
      "pattern_id": 6,
      "pattern_name": "シナリオ判定",
      "difficulty": "★★★",
      "problem_type": "true_false",
      "format": "○×",
      "generated_at": "2025-10-22T12:45:50.696819",
      "problem_text": "【シナリオ】営業者が中古遊技機の取扱いを含む状況で営業を継続することができるか。",
      "correct_answer": "○",
      "explanation": "中古遊技機の取扱いの具体的状況では、適切な対応により営業継続が可能。",
      "source_pdf": 1,
      "source_page": 0,
      "teaching_value": "このパターンは実務的判定を学ぶ上で重要"
    },
    {
      "problem_id": 19,
      "theme_id": 1001,
      "theme_name": "中古遊技機の取扱い",
      "pattern_id": 7,
      "pattern_name": "複合違反",
      "difficulty": "★★★",
      "problem_type": "true_false",
      "format": "○×",
      "generated_at": "2025-10-22T12:45:50.696826",
      "problem_text": "【複合違反】中古遊技機の取扱い違反と営業許可違反が同時に存在する場合、{theme_name}違反の方が重大である。",
      "correct_answer": "×",
      "explanation": "営業許可違反の方が営業全体に関わるため、より重大。",
      "source_pdf": 1,
      "source_page": 0,
      "teaching_value": "このパターンは違反の重大度判定を学ぶ上で重要"
    },
    {
      "problem_id": 20,
      "theme_id": 1001,
      "theme_name": "中古遊技機の取扱い",
      "pattern_id": 8,
      "pattern_name": "数値正確性",
      "difficulty": "★",
      "problem_type": "true_false",
      "format": "○×",
      "generated_at": "2025-10-22T12:45:50.696833",
      "problem_text": "【数値】中古遊技機の取扱いに関する具体的な期限・数値は講習テキストに明記されている。",
      "correct_answer": "○",
      "explanation": "はじめに\n\nばちんこ営業は、それが適正に営まれれば、「適度」に射幸心を\n満たす、国民に身近で手軽で健全な大衆娯楽を提供する営業です。\nパチンコ営業が、このように健金な大抄事楽を提供する産業として\n社会前役割を果たしていくたぬめには、その営業に用いられる遊技機\nが、客の射幸心を過度に詞るととのない、「適度] に射率心を満足\nさせるものであることが必要不可欠です。\n\nこのため、風俗泊業等の規制及び業務に具体的な数値が記載されている。",
      "source_pdf": 1,
      "source_page": 0,
      "teaching_value": "このパターンは細かい知識確認を学ぶ上で重要"
    },
    {
      "problem_id": 21,
      "theme_id": 1001,
      "theme_name": "中古遊技機の取扱い",
      "pattern_id": 9,
      "pattern_name": "理由理解",
      "difficulty": "★★★",
      "problem_type": "true_false",
      "format": "○×",
      "generated_at": "2025-10-22T12:45:50.696841",
      "problem_text": "【理由】中古遊技機の取扱いという規制が存在するのは、遊技業の健全化と不正防止のためである。",
      "correct_answer": "○",
      "explanation": "中古遊技機の取扱いは法制度設計の重要な目的に基づいている。",
      "source_pdf": 1,
      "source_page": 0,
      "teaching_value": "このパターンは法制度設計の理解を学ぶ上で重要"
    },
    {
      "problem_id": 22,
      "theme_id": 1001,
      "theme_name": "中古遊技機の取扱い",
      "pattern_id": 10,
      "pattern_name": "経験陥阱",
      "difficulty": "★★★",
      "problem_type": "true_false",
      "format": "○×",
      "generated_at": "2025-10-22T12:45:50.696848",
      "problem_text": "【経験陥阱】営業経験が長い者でも{theme_name}について誤解している場合がある。",
      "correct_answer": "○",
      "explanation": "中古遊技機の取扱いは実務経験と法律の乖離が生じやすい領域。",
      "source_pdf": 1,
      "source_page": 0,
      "teaching_value": "このパターンは知識修正能力を学ぶ上で重要"
    },
    {
      "problem_id": 23,
      "theme_id": 1001,
      "theme_name": "中古遊技機の取扱い",
      "pattern_id": 11,
      "pattern_name": "改正対応",
      "difficulty": "★★★",
      "problem_type": "true_false",
      "format": "○×",
      "generated_at": "2025-10-22T12:45:50.696854",
      "problem_text": "【改正対応】中古遊技機の取扱いに関する法改正があった場合、既存の許可も新規則が適用される。",
      "correct_answer": "×",
      "explanation": "既存許可は経過措置により保護されることが多い。",
      "source_pdf": 1,
      "source_page": 0,
      "teaching_value": "このパターンは法改正への対応を学ぶ上で重要"
    },
    {
      "problem_id": 24,
      "theme_id": 1001,
      "theme_name": "中古遊技機の取扱い",
      "pattern_id": 12,
      "pattern_name": "複合応用",
      "difficulty": "★★★★",
      "problem_type": "true_false",
      "format": "○×",
      "generated_at": "2025-10-22T12:45:50.696861",
      "problem_text": "【複合応用】中古遊技機の取扱いを含む複雑なシナリオでは、全ての条件を総合的に判断する必要がある。",
      "correct_answer": "○",
      "explanation": "中古遊技機の取扱い単独ではなく、複数要素を統合した判定が要求される。",
      "source_pdf": 1,
      "source_page": 0,
      "teaching_value": "このパターンは複数要素の統合判定を学ぶ上で重要"
    },
    {
      "problem_id": 25,
      "theme_id": 1002,
      "theme_name": "遊技機の保守管理",
      "pattern_id": 1,
      "pattern_name": "基本知識",
      "difficulty": "★",
      "problem_type": "true_false",
      "format": "○×",
      "generated_at": "2025-10-22T12:45:50.696867",
      "problem_text": "【基本知識】遊技機の保守管理について述べている。",
      "correct_answer": "○",
      "explanation": "はじめに\n\nばちんこ営業は、それが適正に営まれれば、「適度」に射幸心を\n満たす、国民に身近で手軽で健全な大衆娯楽を提供する営業です。\nパチンコ営業が、このように健金な大抄事楽を提供する産業として\n社会前役割を果たしていくたぬめには、その営業に用いられる遊技機\nが、客の射幸心を過度に詞るととのない、「適度] に射率心を満足\nさせるものであることが必要不可欠です。\n\nこのため、風俗泊業等の規制及び業務から、遊技機の保守管理は正しい。",
      "source_pdf": 1,
      "source_page": 0,
      "teaching_value": "このパターンは基本的な法律事実を学ぶ上で重要"
    },
    {
      "problem_id": 26,
      "theme_id": 1002,
      "theme_name": "遊技機の保守管理",
      "pattern_id": 2,
      "pattern_name": "ひっかけ",
      "difficulty": "★★",
      "problem_type": "true_false",
      "format": "○×",
      "generated_at": "2025-10-22T12:45:50.696874",
      "problem_text": "【ひっかけ】遊技機の保守管理である場合、自動的に法的ステータスが変化する。",
      "correct_answer": "×",
      "explanation": "「自動的に」という表現は誤り。遊技機の保守管理は状況に応じた判断が必要。",
      "source_pdf": 1,
      "source_page": 0,
      "teaching_value": "このパターンは絶対表現への警戒を学ぶ上で重要"
    },
    {
      "problem_id": 27,
      "theme_id": 1002,
      "theme_name": "遊技機の保守管理",
      "pattern_id": 3,
      "pattern_name": "用語比較",
      "difficulty": "★★",
      "problem_type": "true_false",
      "format": "○×",
      "generated_at": "2025-10-22T12:45:50.696881",
      "problem_text": "【用語比較】遊技機の保守管理と営業許可は、同じ有効期限を持つ。",
      "correct_answer": "×",
      "explanation": "遊技機の保守管理と他の規制では有効期限が異なる。",
      "source_pdf": 1,
      "source_page": 0,
      "teaching_value": "このパターンは概念の区別を学ぶ上で重要"
    },
    {
      "problem_id": 28,
      "theme_id": 1002,
      "theme_name": "遊技機の保守管理",
      "pattern_id": 4,
      "pattern_name": "優先順位",
      "difficulty": "★★",
      "problem_type": "true_false",
      "format": "○×",
      "generated_at": "2025-10-22T12:45:50.696887",
      "problem_text": "【優先順位】遊技機の保守管理に関連する複数の対応が必要な場合、遊技機の保守管理の対応が優先される。",
      "correct_answer": "○",
      "explanation": "遊技機の保守管理は営業継続に直結するため、最優先で対応が必要。",
      "source_pdf": 1,
      "source_page": 0,
      "teaching_value": "このパターンは法律体系の理解を学ぶ上で重要"
    },
    {
      "problem_id": 29,
      "theme_id": 1002,
      "theme_name": "遊技機の保守管理",
      "pattern_id": 5,
      "pattern_name": "時系列理解",
      "difficulty": "★★★",
      "problem_type": "true_false",
      "format": "○×",
      "generated_at": "2025-10-22T12:45:50.696895",
      "problem_text": "【時系列】遊技機の保守管理の条件を満たしてから1年経過時点で、法的ステータスに変化がある。",
      "correct_answer": "○",
      "explanation": "時間経過により遊技機の保守管理に関する法的義務が生じることがある。",
      "source_pdf": 1,
      "source_page": 0,
      "teaching_value": "このパターンは時間経過による変化を学ぶ上で重要"
    },
    {
      "problem_id": 30,
      "theme_id": 1002,
      "theme_name": "遊技機の保守管理",
      "pattern_id": 6,
      "pattern_name": "シナリオ判定",
      "difficulty": "★★★",
      "problem_type": "true_false",
      "format": "○×",
      "generated_at": "2025-10-22T12:45:50.696902",
      "problem_text": "【シナリオ】営業者が遊技機の保守管理を含む状況で営業を継続することができるか。",
      "correct_answer": "○",
      "explanation": "遊技機の保守管理の具体的状況では、適切な対応により営業継続が可能。",
      "source_pdf": 1,
      "source_page": 0,
      "teaching_value": "このパターンは実務的判定を学ぶ上で重要"
    },
    {
      "problem_id": 31,
      "theme_id": 1002,
      "theme_name": "遊技機の保守管理",
      "pattern_id": 7,
      "pattern_name": "複合違反",
      "difficulty": "★★★",
      "problem_type": "true_false",
      "format": "○×",
      "generated_at": "2025-10-22T12:45:50.696908",
      "problem_text": "【複合違反】遊技機の保守管理違反と営業許可違反が同時に存在する場合、{theme_name}違反の方が重大である。",
      "correct_answer": "×",
      "explanation": "営業許可違反の方が営業全体に関わるため、より重大。",
      "source_pdf": 1,
      "source_page": 0,
      "teaching_value": "このパターンは違反の重大度判定を学ぶ上で重要"
    },
    {
      "problem_id": 32,
      "theme_id": 1002,
      "theme_name": "遊技機の保守管理",
      "pattern_id": 8,
      "pattern_name": "数値正確性",
      "difficulty": "★",
      "problem_type": "true_false",
      "format": "○×",
      "generated_at": "2025-10-22T12:45:50.696915",
      "problem_text": "【数値】遊技機の保守管理に関する具体的な期限・数値は講習テキストに明記されている。",
      "correct_answer": "○",
      "explanation": "はじめに\n\nばちんこ営業は、それが適正に営まれれば、「適度」に射幸心を\n満たす、国民に身近で手軽で健全な大衆娯楽を提供する営業です。\nパチンコ営業が、このように健金な大抄事楽を提供する産業として\n社会前役割を果たしていくたぬめには、その営業に用いられる遊技機\nが、客の射幸心を過度に詞るととのない、「適度] に射率心を満足\nさせるものであることが必要不可欠です。\n\nこのため、風俗泊業等の規制及び業務に具体的な数値が記載されている。",
      "source_pdf": 1,
      "source_page": 0,
      "teaching_value": "このパターンは細かい知識確認を学ぶ上で重要"
    },
    {
      "problem_id": 33,
      "theme_id": 1002,
      "theme_name": "遊技機の保守管理",
      "pattern_id": 9,
      "pattern_name": "理由理解",
      "difficulty": "★★★",
      "problem_type": "true_false",
      "format": "○×",
      "generated_at": "2025-10-22T12:45:50.696921",
      "problem_text": "【理由】遊技機の保守管理という規制が存在するのは、遊技業の健全化と不正防止のためである。",
      "correct_answer": "○",
      "explanation": "遊技機の保守管理は法制度設計の重要な目的に基づいている。",
      "source_pdf": 1,
      "source_page": 0,
      "teaching_value": "このパターンは法制度設計の理解を学ぶ上で重要"
    },
    {
      "problem_id": 34,
      "theme_id": 1002,
      "theme_name": "遊技機の保守管理",
      "pattern_id": 10,
      "pattern_name": "経験陥阱",
      "difficulty": "★★★",
      "problem_type": "true_false",
      "format": "○×",
      "generated_at": "2025-10-22T12:45:50.696928",
      "problem_text": "【経験陥阱】営業経験が長い者でも{theme_name}について誤解している場合がある。",
      "correct_answer": "○",
      "explanation": "遊技機の保守管理は実務経験と法律の乖離が生じやすい領域。",
      "source_pdf": 1,
      "source_page": 0,
      "teaching_value": "このパターンは知識修正能力を学ぶ上で重要"
    },
    {
      "problem_id": 35,
      "theme_id": 1002,
      "theme_name": "遊技機の保守管理",
      "pattern_id": 11,
      "pattern_name": "改正対応",
      "difficulty": "★★★",
      "problem_type": "true_false",
      "format": "○×",
      "generated_at": "2025-10-22T12:45:50.696935",
      "problem_text": "【改正対応】遊技機の保守管理に関する法改正があった場合、既存の許可も新規則が適用される。",
      "correct_answer": "×",
      "explanation": "既存許可は経過措置により保護されることが多い。",
      "source_pdf": 1,
      "source_page": 0,
      "teaching_value": "このパターンは法改正への対応を学ぶ上で重要"
    },
    {
      "problem_id": 36,
      "theme_id": 1002,
      "theme_name": "遊技機の保守管理",
      "pattern_id": 12,
      "pattern_name": "複合応用",
      "difficulty": "★★★★",
      "problem_type": "true_false",
      "format": "○×",
      "generated_at": "2025-10-22T12:45:50.696941",
      "problem_text": "【複合応用】遊技機の保守管理を含む複雑なシナリオでは、全ての条件を総合的に判断する必要がある。",
      "correct_answer": "○",
      "explanation": "遊技機の保守管理単独ではなく、複数要素を統合した判定が要求される。",
      "source_pdf": 1,
      "source_page": 0,
      "teaching_value": "このパターンは複数要素の統合判定を学ぶ上で重要"
    },
    {
      "problem_id": 37,
      "theme_id": 1003,
      "theme_name": "不正改造の防止",
      "pattern_id": 1,
      "pattern_name": "基本知識",
      "difficulty": "★",
      "problem_type": "true_false",
      "format": "○×",
      "generated_at": "2025-10-22T12:45:50.696947",
      "problem_text": "【基本知識】不正改造の防止について述べている。",
      "correct_answer": "○",
      "explanation": "はじめに\n\nばちんこ営業は、それが適正に営まれれば、「適度」に射幸心を\n満たす、国民に身近で手軽で健全な大衆娯楽を提供する営業です。\nパチンコ営業が、このように健金な大抄事楽を提供する産業として\n社会前役割を果たしていくたぬめには、その営業に用いられる遊技機\nが、客の射幸心を過度に詞るととのない、「適度] に射率心を満足\nさせるものであることが必要不可欠です。\n\nこのため、風俗泊業等の規制及び業務から、不正改造の防止は正しい。",
      "source_pdf": 1,
      "source_page": 0,
      "teaching_value": "このパターンは基本的な法律事実を学ぶ上で重要"
    },
    {
      "problem_id": 38,
      "theme_id": 1003,
      "theme_name": "不正改造の防止",
      "pattern_id": 2,
      "pattern_name": "ひっかけ",
      "difficulty": "★★",
      "problem_type": "true_false",
      "format": "○×",
      "generated_at": "2025-10-22T12:45:50.696954",
      "problem_text": "【ひっかけ】不正改造の防止である場合、自動的に法的ステータスが変化する。",
      "correct_answer": "×",
      "explanation": "「自動的に」という表現は誤り。不正改造の防止は状況に応じた判断が必要。",
      "source_pdf": 1,
      "source_page": 0,
      "teaching_value": "このパターンは絶対表現への警戒を学ぶ上で重要"
    },
    {
      "problem_id": 39,
      "theme_id": 1003,
      "theme_name": "不正改造の防止",
      "pattern_id": 3,
      "pattern_name": "用語比較",
      "difficulty": "★★",
      "problem_type": "true_false",
      "format": "○×",
      "generated_at": "2025-10-22T12:45:50.696961",
      "problem_text": "【用語比較】不正改造の防止と営業許可は、同じ有効期限を持つ。",
      "correct_answer": "×",
      "explanation": "不正改造の防止と他の規制では有効期限が異なる。",
      "source_pdf": 1,
      "source_page": 0,
      "teaching_value": "このパターンは概念の区別を学ぶ上で重要"
    },
    {
      "problem_id": 40,
      "theme_id": 1003,
      "theme_name": "不正改造の防止",
      "pattern_id": 4,
      "pattern_name": "優先順位",
      "difficulty": "★★",
      "problem_type": "true_false",
      "format": "○×",
      "generated_at": "2025-10-22T12:45:50.696968",
      "problem_text": "【優先順位】不正改造の防止に関連する複数の対応が必要な場合、不正改造の防止の対応が優先される。",
      "correct_answer": "○",
      "explanation": "不正改造の防止は営業継続に直結するため、最優先で対応が必要。",
      "source_pdf": 1,
      "source_page": 0,
      "teaching_value": "このパターンは法律体系の理解を学ぶ上で重要"
    },
    {
      "problem_id": 41,
      "theme_id": 1003,
      "theme_name": "不正改造の防止",
      "pattern_id": 5,
      "pattern_name": "時系列理解",
      "difficulty": "★★★",
      "problem_type": "true_false",
      "format": "○×",
      "generated_at": "2025-10-22T12:45:50.696976",
      "problem_text": "【時系列】不正改造の防止の条件を満たしてから1年経過時点で、法的ステータスに変化がある。",
      "correct_answer": "○",
      "explanation": "時間経過により不正改造の防止に関する法的義務が生じることがある。",
      "source_pdf": 1,
      "source_page": 0,
      "teaching_value": "このパターンは時間経過による変化を学ぶ上で重要"
    },
    {
      "problem_id": 42,
      "theme_id": 1003,
      "theme_name": "不正改造の防止",
      "pattern_id": 6,
      "pattern_name": "シナリオ判定",
      "difficulty": "★★★",
      "problem_type": "true_false",
      "format": "○×",
      "generated_at": "2025-10-22T12:45:50.696983",
      "problem_text": "【シナリオ】営業者が不正改造の防止を含む状況で営業を継続することができるか。",
      "correct_answer": "○",
      "explanation": "不正改造の防止の具体的状況では、適切な対応により営業継続が可能。",
      "source_pdf": 1,
      "source_page": 0,
      "teaching_value": "このパターンは実務的判定を学ぶ上で重要"
    },
    {
      "problem_id": 43,
      "theme_id": 1003,
      "theme_name": "不正改造の防止",
      "pattern_id": 7,
      "pattern_name": "複合違反",
      "difficulty": "★★★",
      "problem_type": "true_false",
      "format": "○×",
      "generated_at": "2025-10-22T12:45:50.696989",
      "problem_text": "【複合違反】不正改造の防止違反と営業許可違反が同時に存在する場合、{theme_name}違反の方が重大である。",
      "correct_answer": "×",
      "explanation": "営業許可違反の方が営業全体に関わるため、より重大。",
      "source_pdf": 1,
      "source_page": 0,
      "teaching_value": "このパターンは違反の重大度判定を学ぶ上で重要"
    },
    {
      "problem_id": 44,
      "theme_id": 1003,
      "theme_name": "不正改造の防止",
      "pattern_id": 8,
      "pattern_name": "数値正確性",
      "difficulty": "★",
      "problem_type": "true_false",
      "format": "○×",
      "generated_at": "2025-10-22T12:45:50.696997",
      "problem_text": "【数値】不正改造の防止に関する具体的な期限・数値は講習テキストに明記されている。",
      "correct_answer": "○",
      "explanation": "はじめに\n\nばちんこ営業は、それが適正に営まれれば、「適度」に射幸心を\n満たす、国民に身近で手軽で健全な大衆娯楽を提供する営業です。\nパチンコ営業が、このように健金な大抄事楽を提供する産業として\n社会前役割を果たしていくたぬめには、その営業に用いられる遊技機\nが、客の射幸心を過度に詞るととのない、「適度] に射率心を満足\nさせるものであることが必要不可欠です。\n\nこのため、風俗泊業等の規制及び業務に具体的な数値が記載されている。",
      "source_pdf": 1,
      "source_page": 0,
      "teaching_value": "このパターンは細かい知識確認を学ぶ上で重要"
    },
    {
      "problem_id": 45,
      "theme_id": 1003,
      "theme_name": "不正改造の防止",
      "pattern_id": 9,
      "pattern_name": "理由理解",
      "difficulty": "★★★",
      "problem_type": "true_false",
      "format": "○×",
      "generated_at": "2025-10-22T12:45:50.697003",
      "problem_text": "【理由】不正改造の防止という規制が存在するのは、遊技業の健全化と不正防止のためである。",
      "correct_answer": "○",
      "explanation": "不正改造の防止は法制度設計の重要な目的に基づいている。",
      "source_pdf": 1,
      "source_page": 0,
      "teaching_value": "このパターンは法制度設計の理解を学ぶ上で重要"
    },
    {
      "problem_id": 46,
      "theme_id": 1003,
      "theme_name": "不正改造の防止",
      "pattern_id": 10,
      "pattern_name": "経験陥阱",
      "difficulty": "★★★",
      "problem_type": "true_false",
      "format": "○×",
      "generated_at": "2025-10-22T12:45:50.697010",
      "problem_text": "【経験陥阱】営業経験が長い者でも{theme_name}について誤解している場合がある。",
      "correct_answer": "○",
      "explanation": "不正改造の防止は実務経験と法律の乖離が生じやすい領域。",
      "source_pdf": 1,
      "source_page": 0,
      "teaching_value": "このパターンは知識修正能力を学ぶ上で重要"
    },
    {
      "problem_id": 47,
      "theme_id": 1003,
      "theme_name": "不正改造の防止",
      "pattern_id": 11,
      "pattern_name": "改正対応",
      "difficulty": "★★★",
      "problem_type": "true_false",
      "format": "○×",
      "generated_at": "2025-10-22T12:45:50.697016",
      "problem_text": "【改正対応】不正改造の防止に関する法改正があった場合、既存の許可も新規則が適用される。",
      "correct_answer": "×",
      "explanation": "既存許可は経過措置により保護されることが多い。",
      "source_pdf": 1,
      "source_page": 0,
      "teaching_value": "このパターンは法改正への対応を学ぶ上で重要"
    },
    {
      "problem_id": 48,
      "theme_id": 1003,
      "theme_name": "不正改造の防止",
      "pattern_id": 12,
      "pattern_name": "複合応用",
      "difficulty": "★★★★",
      "problem_type": "true_false",
      "format": "○×",
      "generated_at": "2025-10-22T12:45:50.697022",
      "problem_text": "【複合応用】不正改造の防止を含む複雑なシナリオでは、全ての条件を総合的に判断する必要がある。",
      "correct_answer": "○",
      "explanation": "不正改造の防止単独ではなく、複数要素を統合した判定が要求される。",
      "source_pdf": 1,
      "source_page": 0,
      "teaching_value": "このパターンは複数要素の統合判定を学ぶ上で重要"
    },
    {
      "problem_id": 49,
      "theme_id": 1004,
      "theme_name": "セキュリティ確保",
      "pattern_id": 1,
      "pattern_name": "基本知識",
      "difficulty": "★",
      "problem_type": "true_false",
      "format": "○×",
      "generated_at": "2025-10-22T12:45:50.697030",
      "problem_text": "【基本知識】セキュリティ確保について述べている。",
      "correct_answer": "○",
      "explanation": "はじめに\n\nばちんこ営業は、それが適正に営まれれば、「適度」に射幸心を\n満たす、国民に身近で手軽で健全な大衆娯楽を提供する営業です。\nパチンコ営業が、このように健金な大抄事楽を提供する産業として\n社会前役割を果たしていくたぬめには、その営業に用いられる遊技機\nが、客の射幸心を過度に詞るととのない、「適度] に射率心を満足\nさせるものであることが必要不可欠です。\n\nこのため、風俗泊業等の規制及び業務から、セキュリティ確保は正しい。",
      "source_pdf": 1,
      "source_page": 0,
      "teaching_value": "このパターンは基本的な法律事実を学ぶ上で重要"
    },
    {
      "problem_id": 50,
      "theme_id": 1004,
      "theme_name": "セキュリティ確保",
      "pattern_id": 2,
      "pattern_name": "ひっかけ",
      "difficulty": "★★",
      "problem_type": "true_false",
      "format": "○×",
      "generated_at": "2025-10-22T12:45:50.697087",
      "problem_text": "【ひっかけ】セキュリティ確保である場合、自動的に法的ステータスが変化する。",
      "correct_answer": "×",
      "explanation": "「自動的に」という表現は誤り。セキュリティ確保は状況に応じた判断が必要。",
      "source_pdf": 1,
      "source_page": 0,
      "teaching_value": "このパターンは絶対表現への警戒を学ぶ上で重要"
    },
    {
      "problem_id": 51,
      "theme_id": 1004,
      "theme_name": "セキュリティ確保",
      "pattern_id": 3,
      "pattern_name": "用語比較",
      "difficulty": "★★",
      "problem_type": "true_false",
      "format": "○×",
      "generated_at": "2025-10-22T12:45:50.697097",
      "problem_text": "【用語比較】セキュリティ確保と営業許可は、同じ有効期限を持つ。",
      "correct_answer": "×",
      "explanation": "セキュリティ確保と他の規制では有効期限が異なる。",
      "source_pdf": 1,
      "source_page": 0,
      "teaching_value": "このパターンは概念の区別を学ぶ上で重要"
    },
    {
      "problem_id": 52,
      "theme_id": 1004,
      "theme_name": "セキュリティ確保",
      "pattern_id": 4,
      "pattern_name": "優先順位",
      "difficulty": "★★",
      "problem_type": "true_false",
      "format": "○×",
      "generated_at": "2025-10-22T12:45:50.697106",
      "problem_text": "【優先順位】セキュリティ確保に関連する複数の対応が必要な場合、セキュリティ確保の対応が優先される。",
      "correct_answer": "○",
      "explanation": "セキュリティ確保は営業継続に直結するため、最優先で対応が必要。",
      "source_pdf": 1,
      "source_page": 0,
      "teaching_value": "このパターンは法律体系の理解を学ぶ上で重要"
    },
    {
      "problem_id": 53,
      "theme_id": 1004,
      "theme_name": "セキュリティ確保",
      "pattern_id": 5,
      "pattern_name": "時系列理解",
      "difficulty": "★★★",
      "problem_type": "true_false",
      "format": "○×",
      "generated_at": "2025-10-22T12:45:50.697113",
      "problem_text": "【時系列】セキュリティ確保の条件を満たしてから1年経過時点で、法的ステータスに変化がある。",
      "correct_answer": "○",
      "explanation": "時間経過によりセキュリティ確保に関する法的義務が生じることがある。",
      "source_pdf": 1,
      "source_page": 0,
      "teaching_value": "このパターンは時間経過による変化を学ぶ上で重要"
    },
    {
      "problem_id": 54,
      "theme_id": 1004,
      "theme_name": "セキュリティ確保",
      "pattern_id": 6,
      "pattern_name": "シナリオ判定",
      "difficulty": "★★★",
      "problem_type": "true_false",
      "format": "○×",
      "generated_at": "2025-10-22T12:45:50.697121",
      "problem_text": "【シナリオ】営業者がセキュリティ確保を含む状況で営業を継続することができるか。",
      "correct_answer": "○",
      "explanation": "セキュリティ確保の具体的状況では、適切な対応により営業継続が可能。",
      "source_pdf": 1,
      "source_page": 0,
      "teaching_value": "このパターンは実務的判定を学ぶ上で重要"
    },
    {
      "problem_id": 55,
      "theme_id": 1004,
      "theme_name": "セキュリティ確保",
      "pattern_id": 7,
      "pattern_name": "複合違反",
      "difficulty": "★★★",
      "problem_type": "true_false",
      "format": "○×",
      "generated_at": "2025-10-22T12:45:50.697127",
      "problem_text": "【複合違反】セキュリティ確保違反と営業許可違反が同時に存在する場合、{theme_name}違反の方が重大である。",
      "correct_answer": "×",
      "explanation": "営業許可違反の方が営業全体に関わるため、より重大。",
      "source_pdf": 1,
      "source_page": 0,
      "teaching_value": "このパターンは違反の重大度判定を学ぶ上で重要"
    },
    {
      "problem_id": 56,
      "theme_id": 1004,
      "theme_name": "セキュリティ確保",
      "pattern_id": 8,
      "pattern_name": "数値正確性",
      "difficulty": "★",
      "problem_type": "true_false",
      "format": "○×",
      "generated_at": "2025-10-22T12:45:50.697134",
      "problem_text": "【数値】セキュリティ確保に関する具体的な期限・数値は講習テキストに明記されている。",
      "correct_answer": "○",
      "explanation": "はじめに\n\nばちんこ営業は、それが適正に営まれれば、「適度」に射幸心を\n満たす、国民に身近で手軽で健全な大衆娯楽を提供する営業です。\nパチンコ営業が、このように健金な大抄事楽を提供する産業として\n社会前役割を果たしていくたぬめには、その営業に用いられる遊技機\nが、客の射幸心を過度に詞るととのない、「適度] に射率心を満足\nさせるものであることが必要不可欠です。\n\nこのため、風俗泊業等の規制及び業務に具体的な数値が記載されている。",
      "source_pdf": 1,
      "source_page": 0,
      "teaching_value": "このパターンは細かい知識確認を学ぶ上で重要"
    },
    {
      "problem_id": 57,
      "theme_id": 1004,
      "theme_name": "セキュリティ確保",
      "pattern_id": 9,
      "pattern_name": "理由理解",
      "difficulty": "★★★",
      "problem_type": "true_false",
      "format": "○×",
      "generated_at": "2025-10-22T12:45:50.697141",
      "problem_text": "【理由】セキュリティ確保という規制が存在するのは、遊技業の健全化と不正防止のためである。",
      "correct_answer": "○",
      "explanation": "セキュリティ確保は法制度設計の重要な目的に基づいている。",
      "source_pdf": 1,
      "source_page": 0,
      "teaching_value": "このパターンは法制度設計の理解を学ぶ上で重要"
    },
    {
      "problem_id": 58,
      "theme_id": 1004,
      "theme_name": "セキュリティ確保",
      "pattern_id": 10,
      "pattern_name": "経験陥阱",
      "difficulty": "★★★",
      "problem_type": "true_false",
      "format": "○×",
      "generated_at": "2025-10-22T12:45:50.697148",
      "problem_text": "【経験陥阱】営業経験が長い者でも{theme_name}について誤解している場合がある。",
      "correct_answer": "○",
      "explanation": "セキュリティ確保は実務経験と法律の乖離が生じやすい領域。",
      "source_pdf": 1,
      "source_page": 0,
      "teaching_value": "このパターンは知識修正能力を学ぶ上で重要"
    },
    {
      "problem_id": 59,
      "theme_id": 1004,
      "theme_name": "セキュリティ確保",
      "pattern_id": 11,
      "pattern_name": "改正対応",
      "difficulty": "★★★",
      "problem_type": "true_false",
      "format": "○×",
      "generated_at": "2025-10-22T12:45:50.697156",
      "problem_text": "【改正対応】セキュリティ確保に関する法改正があった場合、既存の許可も新規則が適用される。",
      "correct_answer": "×",
      "explanation": "既存許可は経過措置により保護されることが多い。",
      "source_pdf": 1,
      "source_page": 0,
      "teaching_value": "このパターンは法改正への対応を学ぶ上で重要"
    },
    {
      "problem_id": 60,
      "theme_id": 1004,
      "theme_name": "セキュリティ確保",
      "pattern_id": 12,
      "pattern_name": "複合応用",
      "difficulty": "★★★★",
      "problem_type": "true_false",
      "format": "○×",
      "generated_at": "2025-10-22T12:45:50.697163",
      "problem_text": "【複合応用】セキュリティ確保を含む複雑なシナリオでは、全ての条件を総合的に判断する必要がある。",
      "correct_answer": "○",
      "explanation": "セキュリティ確保単独ではなく、複数要素を統合した判定が要求される。",
      "source_pdf": 1,
      "source_page": 0,
      "teaching_value": "このパターンは複数要素の統合判定を学ぶ上で重要"
    },
    {
      "problem_id": 61,
      "theme_id": 1005,
      "theme_name": "営業禁止時間",
      "pattern_id": 1,
      "pattern_name": "基本知識",
      "difficulty": "★",
      "problem_type": "true_false",
      "format": "○×",
      "generated_at": "2025-10-22T12:45:50.697171",
      "problem_text": "【基本知識】営業禁止時間について述べている。",
      "correct_answer": "○",
      "explanation": "はじめに\n\nばちんこ営業は、それが適正に営まれれば、「適度」に射幸心を\n満たす、国民に身近で手軽で健全な大衆娯楽を提供する営業です。\nパチンコ営業が、このように健金な大抄事楽を提供する産業として\n社会前役割を果たしていくたぬめには、その営業に用いられる遊技機\nが、客の射幸心を過度に詞るととのない、「適度] に射率心を満足\nさせるものであることが必要不可欠です。\n\nこのため、風俗泊業等の規制及び業務から、営業禁止時間は正しい。",
      "source_pdf": 1,
      "source_page": 0,
      "teaching_value": "このパターンは基本的な法律事実を学ぶ上で重要"
    },
    {
      "problem_id": 62,
      "theme_id": 1005,
      "theme_name": "営業禁止時間",
      "pattern_id": 2,
      "pattern_name": "ひっかけ",
      "difficulty": "★★",
      "problem_type": "true_false",
      "format": "○×",
      "generated_at": "2025-10-22T12:45:50.697177",
      "problem_text": "【ひっかけ】営業禁止時間である場合、自動的に法的ステータスが変化する。",
      "correct_answer": "×",
      "explanation": "「自動的に」という表現は誤り。営業禁止時間は状況に応じた判断が必要。",
      "source_pdf": 1,
      "source_page": 0,
      "teaching_value": "このパターンは絶対表現への警戒を学ぶ上で重要"
    },
    {
      "problem_id": 63,
      "theme_id": 1005,
      "theme_name": "営業禁止時間",
      "pattern_id": 3,
      "pattern_name": "用語比較",
      "difficulty": "★★",
      "problem_type": "true_false",
      "format": "○×",
      "generated_at": "2025-10-22T12:45:50.697184",
      "problem_text": "【用語比較】営業禁止時間と営業許可は、同じ有効期限を持つ。",
      "correct_answer": "×",
      "explanation": "営業禁止時間と他の規制では有効期限が異なる。",
      "source_pdf": 1,
      "source_page": 0,
      "teaching_value": "このパターンは概念の区別を学ぶ上で重要"
    },
    {
      "problem_id": 64,
      "theme_id": 1005,
      "theme_name": "営業禁止時間",
      "pattern_id": 4,
      "pattern_name": "優先順位",
      "difficulty": "★★",
      "problem_type": "true_false",
      "format": "○×",
      "generated_at": "2025-10-22T12:45:50.697192",
      "problem_text": "【優先順位】営業禁止時間に関連する複数の対応が必要な場合、営業禁止時間の対応が優先される。",
      "correct_answer": "○",
      "explanation": "営業禁止時間は営業継続に直結するため、最優先で対応が必要。",
      "source_pdf": 1,
      "source_page": 0,
      "teaching_value": "このパターンは法律体系の理解を学ぶ上で重要"
    },
    {
      "problem_id": 65,
      "theme_id": 1005,
      "theme_name": "営業禁止時間",
      "pattern_id": 5,
      "pattern_name": "時系列理解",
      "difficulty": "★★★",
      "problem_type": "true_false",
      "format": "○×",
      "generated_at": "2025-10-22T12:45:50.697199",
      "problem_text": "【時系列】営業禁止時間の条件を満たしてから1年経過時点で、法的ステータスに変化がある。",
      "correct_answer": "○",
      "explanation": "時間経過により営業禁止時間に関する法的義務が生じることがある。",
      "source_pdf": 1,
      "source_page": 0,
      "teaching_value": "このパターンは時間経過による変化を学ぶ上で重要"
    },
    {
      "problem_id": 66,
      "theme_id": 1005,
      "theme_name": "営業禁止時間",
      "pattern_id": 6,
      "pattern_name": "シナリオ判定",
      "difficulty": "★★★",
      "problem_type": "true_false",
      "format": "○×",
      "generated_at": "2025-10-22T12:45:50.697205",
      "problem_text": "【シナリオ】営業者が営業禁止時間を含む状況で営業を継続することができるか。",
      "correct_answer": "○",
      "explanation": "営業禁止時間の具体的状況では、適切な対応により営業継続が可能。",
      "source_pdf": 1,
      "source_page": 0,
      "teaching_value": "このパターンは実務的判定を学ぶ上で重要"
    },
    {
      "problem_id": 67,
      "theme_id": 1005,
      "theme_name": "営業禁止時間",
      "pattern_id": 7,
      "pattern_name": "複合違反",
      "difficulty": "★★★",
      "problem_type": "true_false",
      "format": "○×",
      "generated_at": "2025-10-22T12:45:50.697212",
      "problem_text": "【複合違反】営業禁止時間違反と営業許可違反が同時に存在する場合、{theme_name}違反の方が重大である。",
      "correct_answer": "×",
      "explanation": "営業許可違反の方が営業全体に関わるため、より重大。",
      "source_pdf": 1,
      "source_page": 0,
      "teaching_value": "このパターンは違反の重大度判定を学ぶ上で重要"
    },
    {
      "problem_id": 68,
      "theme_id": 1005,
      "theme_name": "営業禁止時間",
      "pattern_id": 8,
      "pattern_name": "数値正確性",
      "difficulty": "★",
      "problem_type": "true_false",
      "format": "○×",
      "generated_at": "2025-10-22T12:45:50.697218",
      "problem_text": "【数値】営業禁止時間に関する具体的な期限・数値は講習テキストに明記されている。",
      "correct_answer": "○",
      "explanation": "はじめに\n\nばちんこ営業は、それが適正に営まれれば、「適度」に射幸心を\n満たす、国民に身近で手軽で健全な大衆娯楽を提供する営業です。\nパチンコ営業が、このように健金な大抄事楽を提供する産業として\n社会前役割を果たしていくたぬめには、その営業に用いられる遊技機\nが、客の射幸心を過度に詞るととのない、「適度] に射率心を満足\nさせるものであることが必要不可欠です。\n\nこのため、風俗泊業等の規制及び業務に具体的な数値が記載されている。",
      "source_pdf": 1,
      "source_page": 0,
      "teaching_value": "このパターンは細かい知識確認を学ぶ上で重要"
    },
    {
      "problem_id": 69,
      "theme_id": 1005,
      "theme_name": "営業禁止時間",
      "pattern_id": 9,
      "pattern_name": "理由理解",
      "difficulty": "★★★",
      "problem_type": "true_false",
      "format": "○×",
      "generated_at": "2025-10-22T12:45:50.697226",
      "problem_text": "【理由】営業禁止時間という規制が存在するのは、遊技業の健全化と不正防止のためである。",
      "correct_answer": "○",
      "explanation": "営業禁止時間は法制度設計の重要な目的に基づいている。",
      "source_pdf": 1,
      "source_page": 0,
      "teaching_value": "このパターンは法制度設計の理解を学ぶ上で重要"
    },
    {
      "problem_id": 70,
      "theme_id": 1005,
      "theme_name": "営業禁止時間",
      "pattern_id": 10,
      "pattern_name": "経験陥阱",
      "difficulty": "★★★",
      "problem_type": "true_false",
      "format": "○×",
      "generated_at": "2025-10-22T12:45:50.697232",
      "problem_text": "【経験陥阱】営業経験が長い者でも{theme_name}について誤解している場合がある。",
      "correct_answer": "○",
      "explanation": "営業禁止時間は実務経験と法律の乖離が生じやすい領域。",
      "source_pdf": 1,
      "source_page": 0,
      "teaching_value": "このパターンは知識修正能力を学ぶ上で重要"
    },
    {
      "problem_id": 71,
      "theme_id": 1005,
      "theme_name": "営業禁止時間",
      "pattern_id": 11,
      "pattern_name": "改正対応",
      "difficulty": "★★★",
      "problem_type": "true_false",
      "format": "○×",
      "generated_at": "2025-10-22T12:45:50.697239",
      "problem_text": "【改正対応】営業禁止時間に関する法改正があった場合、既存の許可も新規則が適用される。",
      "correct_answer": "×",
      "explanation": "既存許可は経過措置により保護されることが多い。",
      "source_pdf": 1,
      "source_page": 0,
      "teaching_value": "このパターンは法改正への対応を学ぶ上で重要"
    },
    {
      "problem_id": 72,
      "theme_id": 1005,
      "theme_name": "営業禁止時間",
      "pattern_id": 12,
      "pattern_name": "複合応用",
      "difficulty": "★★★★",
      "problem_type": "true_false",
      "format": "○×",
      "generated_at": "2025-10-22T12:45:50.697245",
      "problem_text": "【複合応用】営業禁止時間を含む複雑なシナリオでは、全ての条件を総合的に判断する必要がある。",
      "correct_answer": "○",
      "explanation": "営業禁止時間単独ではなく、複数要素を統合した判定が要求される。",
      "source_pdf": 1,
      "source_page": 0,
      "teaching_value": "このパターンは複数要素の統合判定を学ぶ上で重要"
    },
    {
      "problem_id": 73,
      "theme_id": 1006,
      "theme_name": "営業停止命令",
      "pattern_id": 1,
      "pattern_name": "基本知識",
      "difficulty": "★",
      "problem_type": "true_false",
      "format": "○×",
      "generated_at": "2025-10-22T12:45:50.697251",
      "problem_text": "【基本知識】営業停止命令について述べている。",
      "correct_answer": "○",
      "explanation": "はじめに\n\nばちんこ営業は、それが適正に営まれれば、「適度」に射幸心を\n満たす、国民に身近で手軽で健全な大衆娯楽を提供する営業です。\nパチンコ営業が、このように健金な大抄事楽を提供する産業として\n社会前役割を果たしていくたぬめには、その営業に用いられる遊技機\nが、客の射幸心を過度に詞るととのない、「適度] に射率心を満足\nさせるものであることが必要不可欠です。\n\nこのため、風俗泊業等の規制及び業務から、営業停止命令は正しい。",
      "source_pdf": 1,
      "source_page": 0,
      "teaching_value": "このパターンは基本的な法律事実を学ぶ上で重要"
    },
    {
      "problem_id": 74,
      "theme_id": 1006,
      "theme_name": "営業停止命令",
      "pattern_id": 2,
      "pattern_name": "ひっかけ",
      "difficulty": "★★",
      "problem_type": "true_false",
      "format": "○×",
      "generated_at": "2025-10-22T12:45:50.697258",
      "problem_text": "【ひっかけ】営業停止命令である場合、自動的に法的ステータスが変化する。",
      "correct_answer": "×",
      "explanation": "「自動的に」という表現は誤り。営業停止命令は状況に応じた判断が必要。",
      "source_pdf": 1,
      "source_page": 0,
      "teaching_value": "このパターンは絶対表現への警戒を学ぶ上で重要"
    },
    {
      "problem_id": 75,
      "theme_id": 1006,
      "theme_name": "営業停止命令",
      "pattern_id": 3,
      "pattern_name": "用語比較",
      "difficulty": "★★",
      "problem_type": "true_false",
      "format": "○×",
      "generated_at": "2025-10-22T12:45:50.697264",
      "problem_text": "【用語比較】営業停止命令と営業許可は、同じ有効期限を持つ。",
      "correct_answer": "×",
      "explanation": "営業停止命令と他の規制では有効期限が異なる。",
      "source_pdf": 1,
      "source_page": 0,
      "teaching_value": "このパターンは概念の区別を学ぶ上で重要"
    },
    {
      "problem_id": 76,
      "theme_id": 1006,
      "theme_name": "営業停止命令",
      "pattern_id": 4,
      "pattern_name": "優先順位",
      "difficulty": "★★",
      "problem_type": "true_false",
      "format": "○×",
      "generated_at": "2025-10-22T12:45:50.697271",
      "problem_text": "【優先順位】営業停止命令に関連する複数の対応が必要な場合、営業停止命令の対応が優先される。",
      "correct_answer": "○",
      "explanation": "営業停止命令は営業継続に直結するため、最優先で対応が必要。",
      "source_pdf": 1,
      "source_page": 0,
      "teaching_value": "このパターンは法律体系の理解を学ぶ上で重要"
    },
    {
      "problem_id": 77,
      "theme_id": 1006,
      "theme_name": "営業停止命令",
      "pattern_id": 5,
      "pattern_name": "時系列理解",
      "difficulty": "★★★",
      "problem_type": "true_false",
      "format": "○×",
      "generated_at": "2025-10-22T12:45:50.697277",
      "problem_text": "【時系列】営業停止命令の条件を満たしてから1年経過時点で、法的ステータスに変化がある。",
      "correct_answer": "○",
      "explanation": "時間経過により営業停止命令に関する法的義務が生じることがある。",
      "source_pdf": 1,
      "source_page": 0,
      "teaching_value": "このパターンは時間経過による変化を学ぶ上で重要"
    },
    {
      "problem_id": 78,
      "theme_id": 1006,
      "theme_name": "営業停止命令",
      "pattern_id": 6,
      "pattern_name": "シナリオ判定",
      "difficulty": "★★★",
      "problem_type": "true_false",
      "format": "○×",
      "generated_at": "2025-10-22T12:45:50.697283",
      "problem_text": "【シナリオ】営業者が営業停止命令を含む状況で営業を継続することができるか。",
      "correct_answer": "○",
      "explanation": "営業停止命令の具体的状況では、適切な対応により営業継続が可能。",
      "source_pdf": 1,
      "source_page": 0,
      "teaching_value": "このパターンは実務的判定を学ぶ上で重要"
    },
    {
      "problem_id": 79,
      "theme_id": 1006,
      "theme_name": "営業停止命令",
      "pattern_id": 7,
      "pattern_name": "複合違反",
      "difficulty": "★★★",
      "problem_type": "true_false",
      "format": "○×",
      "generated_at": "2025-10-22T12:45:50.697291",
      "problem_text": "【複合違反】営業停止命令違反と営業許可違反が同時に存在する場合、{theme_name}違反の方が重大である。",
      "correct_answer": "×",
      "explanation": "営業許可違反の方が営業全体に関わるため、より重大。",
      "source_pdf": 1,
      "source_page": 0,
      "teaching_value": "このパターンは違反の重大度判定を学ぶ上で重要"
    },
    {
      "problem_id": 80,
      "theme_id": 1006,
      "theme_name": "営業停止命令",
      "pattern_id": 8,
      "pattern_name": "数値正確性",
      "difficulty": "★",
      "problem_type": "true_false",
      "format": "○×",
      "generated_at": "2025-10-22T12:45:50.697297",
      "problem_text": "【数値】営業停止命令に関する具体的な期限・数値は講習テキストに明記されている。",
      "correct_answer": "○",
      "explanation": "はじめに\n\nばちんこ営業は、それが適正に営まれれば、「適度」に射幸心を\n満たす、国民に身近で手軽で健全な大衆娯楽を提供する営業です。\nパチンコ営業が、このように健金な大抄事楽を提供する産業として\n社会前役割を果たしていくたぬめには、その営業に用いられる遊技機\nが、客の射幸心を過度に詞るととのない、「適度] に射率心を満足\nさせるものであることが必要不可欠です。\n\nこのため、風俗泊業等の規制及び業務に具体的な数値が記載されている。",
      "source_pdf": 1,
      "source_page": 0,
      "teaching_value": "このパターンは細かい知識確認を学ぶ上で重要"
    },
    {
      "problem_id": 81,
      "theme_id": 1006,
      "theme_name": "営業停止命令",
      "pattern_id": 9,
      "pattern_name": "理由理解",
      "difficulty": "★★★",
      "problem_type": "true_false",
      "format": "○×",
      "generated_at": "2025-10-22T12:45:50.697304",
      "problem_text": "【理由】営業停止命令という規制が存在するのは、遊技業の健全化と不正防止のためである。",
      "correct_answer": "○",
      "explanation": "営業停止命令は法制度設計の重要な目的に基づいている。",
      "source_pdf": 1,
      "source_page": 0,
      "teaching_value": "このパターンは法制度設計の理解を学ぶ上で重要"
    },
    {
      "problem_id": 82,
      "theme_id": 1006,
      "theme_name": "営業停止命令",
      "pattern_id": 10,
      "pattern_name": "経験陥阱",
      "difficulty": "★★★",
      "problem_type": "true_false",
      "format": "○×",
      "generated_at": "2025-10-22T12:45:50.697310",
      "problem_text": "【経験陥阱】営業経験が長い者でも{theme_name}について誤解している場合がある。",
      "correct_answer": "○",
      "explanation": "営業停止命令は実務経験と法律の乖離が生じやすい領域。",
      "source_pdf": 1,
      "source_page": 0,
      "teaching_value": "このパターンは知識修正能力を学ぶ上で重要"
    },
    {
      "problem_id": 83,
      "theme_id": 1006,
      "theme_name": "営業停止命令",
      "pattern_id": 11,
      "pattern_name": "改正対応",
      "difficulty": "★★★",
      "problem_type": "true_false",
      "format": "○×",
      "generated_at": "2025-10-22T12:45:50.697317",
      "problem_text": "【改正対応】営業停止命令に関する法改正があった場合、既存の許可も新規則が適用される。",
      "correct_answer": "×",
      "explanation": "既存許可は経過措置により保護されることが多い。",
      "source_pdf": 1,
      "source_page": 0,
      "teaching_value": "このパターンは法改正への対応を学ぶ上で重要"
    },
    {
      "problem_id": 84,
      "theme_id": 1006,
      "theme_name": "営業停止命令",
      "pattern_id": 12,
      "pattern_name": "複合応用",
      "difficulty": "★★★★",
      "problem_type": "true_false",
      "format": "○×",
      "generated_at": "2025-10-22T12:45:50.697323",
      "problem_text": "【複合応用】営業停止命令を含む複雑なシナリオでは、全ての条件を総合的に判断する必要がある。",
      "correct_answer": "○",
      "explanation": "営業停止命令単独ではなく、複数要素を統合した判定が要求される。",
      "source_pdf": 1,
      "source_page": 0,
      "teaching_value": "このパターンは複数要素の統合判定を学ぶ上で重要"
    },
    {
      "problem_id": 85,
      "theme_id": 1007,
      "theme_name": "営業許可は無期限有効",
      "pattern_id": 1,
      "pattern_name": "基本知識",
      "difficulty": "★",
      "problem_type": "true_false",
      "format": "○×",
      "generated_at": "2025-10-22T12:45:50.697329",
      "problem_text": "【基本知識】営業許可は無期限有効について述べている。",
      "correct_answer": "○",
      "explanation": "はじめに\n\nばちんこ営業は、それが適正に営まれれば、「適度」に射幸心を\n満たす、国民に身近で手軽で健全な大衆娯楽を提供する営業です。\nパチンコ営業が、このように健金な大抄事楽を提供する産業として\n社会前役割を果たしていくたぬめには、その営業に用いられる遊技機\nが、客の射幸心を過度に詞るととのない、「適度] に射率心を満足\nさせるものであることが必要不可欠です。\n\nこのため、風俗泊業等の規制及び業務から、営業許可は無期限有効は正しい。",
      "source_pdf": 1,
      "source_page": 0,
      "teaching_value": "このパターンは基本的な法律事実を学ぶ上で重要"
    },
    {
      "problem_id": 86,
      "theme_id": 1007,
      "theme_name": "営業許可は無期限有効",
      "pattern_id": 2,
      "pattern_name": "ひっかけ",
      "difficulty": "★★",
      "problem_type": "true_false",
      "format": "○×",
      "generated_at": "2025-10-22T12:45:50.697336",
      "problem_text": "【ひっかけ】営業許可は無期限有効である場合、自動的に法的ステータスが変化する。",
      "correct_answer": "×",
      "explanation": "「自動的に」という表現は誤り。営業許可は無期限有効は状況に応じた判断が必要。",
      "source_pdf": 1,
      "source_page": 0,
      "teaching_value": "このパターンは絶対表現への警戒を学ぶ上で重要"
    },
    {
      "problem_id": 87,
      "theme_id": 1007,
      "theme_name": "営業許可は無期限有効",
      "pattern_id": 3,
      "pattern_name": "用語比較",
      "difficulty": "★★",
      "problem_type": "true_false",
      "format": "○×",
      "generated_at": "2025-10-22T12:45:50.697343",
      "problem_text": "【用語比較】営業許可は無期限有効と営業許可は、同じ有効期限を持つ。",
      "correct_answer": "×",
      "explanation": "営業許可は無期限有効と他の規制では有効期限が異なる。",
      "source_pdf": 1,
      "source_page": 0,
      "teaching_value": "このパターンは概念の区別を学ぶ上で重要"
    },
    {
      "problem_id": 88,
      "theme_id": 1007,
      "theme_name": "営業許可は無期限有効",
      "pattern_id": 4,
      "pattern_name": "優先順位",
      "difficulty": "★★",
      "problem_type": "true_false",
      "format": "○×",
      "generated_at": "2025-10-22T12:45:50.697350",
      "problem_text": "【優先順位】営業許可は無期限有効に関連する複数の対応が必要な場合、営業許可は無期限有効の対応が優先される。",
      "correct_answer": "○",
      "explanation": "営業許可は無期限有効は営業継続に直結するため、最優先で対応が必要。",
      "source_pdf": 1,
      "source_page": 0,
      "teaching_value": "このパターンは法律体系の理解を学ぶ上で重要"
    },
    {
      "problem_id": 89,
      "theme_id": 1007,
      "theme_name": "営業許可は無期限有効",
      "pattern_id": 5,
      "pattern_name": "時系列理解",
      "difficulty": "★★★",
      "problem_type": "true_false",
      "format": "○×",
      "generated_at": "2025-10-22T12:45:50.697358",
      "problem_text": "【時系列】営業許可は無期限有効の条件を満たしてから1年経過時点で、法的ステータスに変化がある。",
      "correct_answer": "○",
      "explanation": "時間経過により営業許可は無期限有効に関する法的義務が生じることがある。",
      "source_pdf": 1,
      "source_page": 0,
      "teaching_value": "このパターンは時間経過による変化を学ぶ上で重要"
    },
    {
      "problem_id": 90,
      "theme_id": 1007,
      "theme_name": "営業許可は無期限有効",
      "pattern_id": 6,
      "pattern_name": "シナリオ判定",
      "difficulty": "★★★",
      "problem_type": "true_false",
      "format": "○×",
      "generated_at": "2025-10-22T12:45:50.697364",
      "problem_text": "【シナリオ】営業者が営業許可は無期限有効を含む状況で営業を継続することができるか。",
      "correct_answer": "○",
      "explanation": "営業許可は無期限有効の具体的状況では、適切な対応により営業継続が可能。",
      "source_pdf": 1,
      "source_page": 0,
      "teaching_value": "このパターンは実務的判定を学ぶ上で重要"
    },
    {
      "problem_id": 91,
      "theme_id": 1007,
      "theme_name": "営業許可は無期限有効",
      "pattern_id": 7,
      "pattern_name": "複合違反",
      "difficulty": "★★★",
      "problem_type": "true_false",
      "format": "○×",
      "generated_at": "2025-10-22T12:45:50.697372",
      "problem_text": "【複合違反】営業許可は無期限有効違反と営業許可違反が同時に存在する場合、{theme_name}違反の方が重大である。",
      "correct_answer": "×",
      "explanation": "営業許可違反の方が営業全体に関わるため、より重大。",
      "source_pdf": 1,
      "source_page": 0,
      "teaching_value": "このパターンは違反の重大度判定を学ぶ上で重要"
    },
    {
      "problem_id": 92,
      "theme_id": 1007,
      "theme_name": "営業許可は無期限有効",
      "pattern_id": 8,
      "pattern_name": "数値正確性",
      "difficulty": "★",
      "problem_type": "true_false",
      "format": "○×",
      "generated_at": "2025-10-22T12:45:50.697378",
      "problem_text": "【数値】営業許可は無期限有効に関する具体的な期限・数値は講習テキストに明記されている。",
      "correct_answer": "○",
      "explanation": "はじめに\n\nばちんこ営業は、それが適正に営まれれば、「適度」に射幸心を\n満たす、国民に身近で手軽で健全な大衆娯楽を提供する営業です。\nパチンコ営業が、このように健金な大抄事楽を提供する産業として\n社会前役割を果たしていくたぬめには、その営業に用いられる遊技機\nが、客の射幸心を過度に詞るととのない、「適度] に射率心を満足\nさせるものであることが必要不可欠です。\n\nこのため、風俗泊業等の規制及び業務に具体的な数値が記載されている。",
      "source_pdf": 1,
      "source_page": 0,
      "teaching_value": "このパターンは細かい知識確認を学ぶ上で重要"
    },
    {
      "problem_id": 93,
      "theme_id": 1007,
      "theme_name": "営業許可は無期限有効",
      "pattern_id": 9,
      "pattern_name": "理由理解",
      "difficulty": "★★★",
      "problem_type": "true_false",
      "format": "○×",
      "generated_at": "2025-10-22T12:45:50.697385",
      "problem_text": "【理由】営業許可は無期限有効という規制が存在するのは、遊技業の健全化と不正防止のためである。",
      "correct_answer": "○",
      "explanation": "営業許可は無期限有効は法制度設計の重要な目的に基づいている。",
      "source_pdf": 1,
      "source_page": 0,
      "teaching_value": "このパターンは法制度設計の理解を学ぶ上で重要"
    },
    {
      "problem_id": 94,
      "theme_id": 1007,
      "theme_name": "営業許可は無期限有効",
      "pattern_id": 10,
      "pattern_name": "経験陥阱",
      "difficulty": "★★★",
      "problem_type": "true_false",
      "format": "○×",
      "generated_at": "2025-10-22T12:45:50.697392",
      "problem_text": "【経験陥阱】営業経験が長い者でも{theme_name}について誤解している場合がある。",
      "correct_answer": "○",
      "explanation": "営業許可は無期限有効は実務経験と法律の乖離が生じやすい領域。",
      "source_pdf": 1,
      "source_page": 0,
      "teaching_value": "このパターンは知識修正能力を学ぶ上で重要"
    },
    {
      "problem_id": 95,
      "theme_id": 1007,
      "theme_name": "営業許可は無期限有効",
      "pattern_id": 11,
      "pattern_name": "改正対応",
      "difficulty": "★★★",
      "problem_type": "true_false",
      "format": "○×",
      "generated_at": "2025-10-22T12:45:50.697398",
      "problem_text": "【改正対応】営業許可は無期限有効に関する法改正があった場合、既存の許可も新規則が適用される。",
      "correct_answer": "×",
      "explanation": "既存許可は経過措置により保護されることが多い。",
      "source_pdf": 1,
      "source_page": 0,
      "teaching_value": "このパターンは法改正への対応を学ぶ上で重要"
    },
    {
      "problem_id": 96,
      "theme_id": 1007,
      "theme_name": "営業許可は無期限有効",
      "pattern_id": 12,
      "pattern_name": "複合応用",
      "difficulty": "★★★★",
      "problem_type": "true_false",
      "format": "○×",
      "generated_at": "2025-10-22T12:45:50.697405",
      "problem_text": "【複合応用】営業許可は無期限有効を含む複雑なシナリオでは、全ての条件を総合的に判断する必要がある。",
      "correct_answer": "○",
      "explanation": "営業許可は無期限有効単独ではなく、複数要素を統合した判定が要求される。",
      "source_pdf": 1,
      "source_page": 0,
      "teaching_value": "このパターンは複数要素の統合判定を学ぶ上で重要"
    },
    {
      "problem_id": 97,
      "theme_id": 1008,
      "theme_name": "営業許可と型式検定の違い",
      "pattern_id": 1,
      "pattern_name": "基本知識",
      "difficulty": "★",
      "problem_type": "true_false",
      "format": "○×",
      "generated_at": "2025-10-22T12:45:50.697412",
      "problem_text": "【基本知識】営業許可と型式検定の違いについて述べている。",
      "correct_answer": "○",
      "explanation": "はじめに\n\nばちんこ営業は、それが適正に営まれれば、「適度」に射幸心を\n満たす、国民に身近で手軽で健全な大衆娯楽を提供する営業です。\nパチンコ営業が、このように健金な大抄事楽を提供する産業として\n社会前役割を果たしていくたぬめには、その営業に用いられる遊技機\nが、客の射幸心を過度に詞るととのない、「適度] に射率心を満足\nさせるものであることが必要不可欠です。\n\nこのため、風俗泊業等の規制及び業務から、営業許可と型式検定の違いは正しい。",
      "source_pdf": 1,
      "source_page": 0,
      "teaching_value": "このパターンは基本的な法律事実を学ぶ上で重要"
    },
    {
      "problem_id": 98,
      "theme_id": 1008,
      "theme_name": "営業許可と型式検定の違い",
      "pattern_id": 2,
      "pattern_name": "ひっかけ",
      "difficulty": "★★",
      "problem_type": "true_false",
      "format": "○×",
      "generated_at": "2025-10-22T12:45:50.697419",
      "problem_text": "【ひっかけ】営業許可と型式検定の違いである場合、自動的に法的ステータスが変化する。",
      "correct_answer": "×",
      "explanation": "「自動的に」という表現は誤り。営業許可と型式検定の違いは状況に応じた判断が必要。",
      "source_pdf": 1,
      "source_page": 0,
      "teaching_value": "このパターンは絶対表現への警戒を学ぶ上で重要"
    },
    {
      "problem_id": 99,
      "theme_id": 1008,
      "theme_name": "営業許可と型式検定の違い",
      "pattern_id": 3,
      "pattern_name": "用語比較",
      "difficulty": "★★",
      "problem_type": "true_false",
      "format": "○×",
      "generated_at": "2025-10-22T12:45:50.697425",
      "problem_text": "【用語比較】営業許可と型式検定の違いと営業許可は、同じ有効期限を持つ。",
      "correct_answer": "×",
      "explanation": "営業許可と型式検定の違いと他の規制では有効期限が異なる。",
      "source_pdf": 1,
      "source_page": 0,
      "teaching_value": "このパターンは概念の区別を学ぶ上で重要"
    },
    {
      "problem_id": 100,
      "theme_id": 1008,
      "theme_name": "営業許可と型式検定の違い",
      "pattern_id": 4,
      "pattern_name": "優先順位",
      "difficulty": "★★",
      "problem_type": "true_false",
      "format": "○×",
      "generated_at": "2025-10-22T12:45:50.697463",
      "problem_text": "【優先順位】営業許可と型式検定の違いに関連する複数の対応が必要な場合、営業許可と型式検定の違いの対応が優先される。",
      "correct_answer": "○",
      "explanation": "営業許可と型式検定の違いは営業継続に直結するため、最優先で対応が必要。",
      "source_pdf": 1,
      "source_page": 0,
      "teaching_value": "このパターンは法律体系の理解を学ぶ上で重要"
    },
    {
      "problem_id": 101,
      "theme_id": 1008,
      "theme_name": "営業許可と型式検定の違い",
      "pattern_id": 5,
      "pattern_name": "時系列理解",
      "difficulty": "★★★",
      "problem_type": "true_false",
      "format": "○×",
      "generated_at": "2025-10-22T12:45:50.697473",
      "problem_text": "【時系列】営業許可と型式検定の違いの条件を満たしてから1年経過時点で、法的ステータスに変化がある。",
      "correct_answer": "○",
      "explanation": "時間経過により営業許可と型式検定の違いに関する法的義務が生じることがある。",
      "source_pdf": 1,
      "source_page": 0,
      "teaching_value": "このパターンは時間経過による変化を学ぶ上で重要"
    },
    {
      "problem_id": 102,
      "theme_id": 1008,
      "theme_name": "営業許可と型式検定の違い",
      "pattern_id": 6,
      "pattern_name": "シナリオ判定",
      "difficulty": "★★★",
      "problem_type": "true_false",
      "format": "○×",
      "generated_at": "2025-10-22T12:45:50.697482",
      "problem_text": "【シナリオ】営業者が営業許可と型式検定の違いを含む状況で営業を継続することができるか。",
      "correct_answer": "○",
      "explanation": "営業許可と型式検定の違いの具体的状況では、適切な対応により営業継続が可能。",
      "source_pdf": 1,
      "source_page": 0,
      "teaching_value": "このパターンは実務的判定を学ぶ上で重要"
    },
    {
      "problem_id": 103,
      "theme_id": 1008,
      "theme_name": "営業許可と型式検定の違い",
      "pattern_id": 7,
      "pattern_name": "複合違反",
      "difficulty": "★★★",
      "problem_type": "true_false",
      "format": "○×",
      "generated_at": "2025-10-22T12:45:50.697489",
      "problem_text": "【複合違反】営業許可と型式検定の違い違反と営業許可違反が同時に存在する場合、{theme_name}違反の方が重大である。",
      "correct_answer": "×",
      "explanation": "営業許可違反の方が営業全体に関わるため、より重大。",
      "source_pdf": 1,
      "source_page": 0,
      "teaching_value": "このパターンは違反の重大度判定を学ぶ上で重要"
    },
    {
      "problem_id": 104,
      "theme_id": 1008,
      "theme_name": "営業許可と型式検定の違い",
      "pattern_id": 8,
      "pattern_name": "数値正確性",
      "difficulty": "★",
      "problem_type": "true_false",
      "format": "○×",
      "generated_at": "2025-10-22T12:45:50.697496",
      "problem_text": "【数値】営業許可と型式検定の違いに関する具体的な期限・数値は講習テキストに明記されている。",
      "correct_answer": "○",
      "explanation": "はじめに\n\nばちんこ営業は、それが適正に営まれれば、「適度」に射幸心を\n満たす、国民に身近で手軽で健全な大衆娯楽を提供する営業です。\nパチンコ営業が、このように健金な大抄事楽を提供する産業として\n社会前役割を果たしていくたぬめには、その営業に用いられる遊技機\nが、客の射幸心を過度に詞るととのない、「適度] に射率心を満足\nさせるものであることが必要不可欠です。\n\nこのため、風俗泊業等の規制及び業務に具体的な数値が記載されている。",
      "source_pdf": 1,
      "source_page": 0,
      "teaching_value": "このパターンは細かい知識確認を学ぶ上で重要"
    },
    {
      "problem_id": 105,
      "theme_id": 1008,
      "theme_name": "営業許可と型式検定の違い",
      "pattern_id": 9,
      "pattern_name": "理由理解",
      "difficulty": "★★★",
      "problem_type": "true_false",
      "format": "○×",
      "generated_at": "2025-10-22T12:45:50.697504",
      "problem_text": "【理由】営業許可と型式検定の違いという規制が存在するのは、遊技業の健全化と不正防止のためである。",
      "correct_answer": "○",
      "explanation": "営業許可と型式検定の違いは法制度設計の重要な目的に基づいている。",
      "source_pdf": 1,
      "source_page": 0,
      "teaching_value": "このパターンは法制度設計の理解を学ぶ上で重要"
    },
    {
      "problem_id": 106,
      "theme_id": 1008,
      "theme_name": "営業許可と型式検定の違い",
      "pattern_id": 10,
      "pattern_name": "経験陥阱",
      "difficulty": "★★★",
      "problem_type": "true_false",
      "format": "○×",
      "generated_at": "2025-10-22T12:45:50.697510",
      "problem_text": "【経験陥阱】営業経験が長い者でも{theme_name}について誤解している場合がある。",
      "correct_answer": "○",
      "explanation": "営業許可と型式検定の違いは実務経験と法律の乖離が生じやすい領域。",
      "source_pdf": 1,
      "source_page": 0,
      "teaching_value": "このパターンは知識修正能力を学ぶ上で重要"
    },
    {
      "problem_id": 107,
      "theme_id": 1008,
      "theme_name": "営業許可と型式検定の違い",
      "pattern_id": 11,
      "pattern_name": "改正対応",
      "difficulty": "★★★",
      "problem_type": "true_false",
      "format": "○×",
      "generated_at": "2025-10-22T12:45:50.697517",
      "problem_text": "【改正対応】営業許可と型式検定の違いに関する法改正があった場合、既存の許可も新規則が適用される。",
      "correct_answer": "×",
      "explanation": "既存許可は経過措置により保護されることが多い。",
      "source_pdf": 1,
      "source_page": 0,
      "teaching_value": "このパターンは法改正への対応を学ぶ上で重要"
    },
    {
      "problem_id": 108,
      "theme_id": 1008,
      "theme_name": "営業許可と型式検定の違い",
      "pattern_id": 12,
      "pattern_name": "複合応用",
      "difficulty": "★★★★",
      "problem_type": "true_false",
      "format": "○×",
      "generated_at": "2025-10-22T12:45:50.697524",
      "problem_text": "【複合応用】営業許可と型式検定の違いを含む複雑なシナリオでは、全ての条件を総合的に判断する必要がある。",
      "correct_answer": "○",
      "explanation": "営業許可と型式検定の違い単独ではなく、複数要素を統合した判定が要求される。",
      "source_pdf": 1,
      "source_page": 0,
      "teaching_value": "このパターンは複数要素の統合判定を学ぶ上で重要"
    },
    {
      "problem_id": 109,
      "theme_id": 1009,
      "theme_name": "遊技機型式検定は3年有効",
      "pattern_id": 1,
      "pattern_name": "基本知識",
      "difficulty": "★",
      "problem_type": "true_false",
      "format": "○×",
      "generated_at": "2025-10-22T12:45:50.697532",
      "problem_text": "【基本知識】遊技機型式検定は3年有効について述べている。",
      "correct_answer": "○",
      "explanation": "はじめに\n\nばちんこ営業は、それが適正に営まれれば、「適度」に射幸心を\n満たす、国民に身近で手軽で健全な大衆娯楽を提供する営業です。\nパチンコ営業が、このように健金な大抄事楽を提供する産業として\n社会前役割を果たしていくたぬめには、その営業に用いられる遊技機\nが、客の射幸心を過度に詞るととのない、「適度] に射率心を満足\nさせるものであることが必要不可欠です。\n\nこのため、風俗泊業等の規制及び業務から、遊技機型式検定は3年有効は正しい。",
      "source_pdf": 1,
      "source_page": 0,
      "teaching_value": "このパターンは基本的な法律事実を学ぶ上で重要"
    },
    {
      "problem_id": 110,
      "theme_id": 1009,
      "theme_name": "遊技機型式検定は3年有効",
      "pattern_id": 2,
      "pattern_name": "ひっかけ",
      "difficulty": "★★",
      "problem_type": "true_false",
      "format": "○×",
      "generated_at": "2025-10-22T12:45:50.697539",
      "problem_text": "【ひっかけ】遊技機型式検定は3年有効である場合、自動的に法的ステータスが変化する。",
      "correct_answer": "×",
      "explanation": "「自動的に」という表現は誤り。遊技機型式検定は3年有効は状況に応じた判断が必要。",
      "source_pdf": 1,
      "source_page": 0,
      "teaching_value": "このパターンは絶対表現への警戒を学ぶ上で重要"
    },
    {
      "problem_id": 111,
      "theme_id": 1009,
      "theme_name": "遊技機型式検定は3年有効",
      "pattern_id": 3,
      "pattern_name": "用語比較",
      "difficulty": "★★",
      "problem_type": "true_false",
      "format": "○×",
      "generated_at": "2025-10-22T12:45:50.697546",
      "problem_text": "【用語比較】遊技機型式検定は3年有効と営業許可は、同じ有効期限を持つ。",
      "correct_answer": "×",
      "explanation": "遊技機型式検定は3年有効と他の規制では有効期限が異なる。",
      "source_pdf": 1,
      "source_page": 0,
      "teaching_value": "このパターンは概念の区別を学ぶ上で重要"
    },
    {
      "problem_id": 112,
      "theme_id": 1009,
      "theme_name": "遊技機型式検定は3年有効",
      "pattern_id": 4,
      "pattern_name": "優先順位",
      "difficulty": "★★",
      "problem_type": "true_false",
      "format": "○×",
      "generated_at": "2025-10-22T12:45:50.697552",
      "problem_text": "【優先順位】遊技機型式検定は3年有効に関連する複数の対応が必要な場合、遊技機型式検定は3年有効の対応が優先される。",
      "correct_answer": "○",
      "explanation": "遊技機型式検定は3年有効は営業継続に直結するため、最優先で対応が必要。",
      "source_pdf": 1,
      "source_page": 0,
      "teaching_value": "このパターンは法律体系の理解を学ぶ上で重要"
    },
    {
      "problem_id": 113,
      "theme_id": 1009,
      "theme_name": "遊技機型式検定は3年有効",
      "pattern_id": 5,
      "pattern_name": "時系列理解",
      "difficulty": "★★★",
      "problem_type": "true_false",
      "format": "○×",
      "generated_at": "2025-10-22T12:45:50.697559",
      "problem_text": "【時系列】遊技機型式検定は3年有効の条件を満たしてから1年経過時点で、法的ステータスに変化がある。",
      "correct_answer": "○",
      "explanation": "時間経過により遊技機型式検定は3年有効に関する法的義務が生じることがある。",
      "source_pdf": 1,
      "source_page": 0,
      "teaching_value": "このパターンは時間経過による変化を学ぶ上で重要"
    },
    {
      "problem_id": 114,
      "theme_id": 1009,
      "theme_name": "遊技機型式検定は3年有効",
      "pattern_id": 6,
      "pattern_name": "シナリオ判定",
      "difficulty": "★★★",
      "problem_type": "true_false",
      "format": "○×",
      "generated_at": "2025-10-22T12:45:50.697565",
      "problem_text": "【シナリオ】営業者が遊技機型式検定は3年有効を含む状況で営業を継続することができるか。",
      "correct_answer": "○",
      "explanation": "遊技機型式検定は3年有効の具体的状況では、適切な対応により営業継続が可能。",
      "source_pdf": 1,
      "source_page": 0,
      "teaching_value": "このパターンは実務的判定を学ぶ上で重要"
    },
    {
      "problem_id": 115,
      "theme_id": 1009,
      "theme_name": "遊技機型式検定は3年有効",
      "pattern_id": 7,
      "pattern_name": "複合違反",
      "difficulty": "★★★",
      "problem_type": "true_false",
      "format": "○×",
      "generated_at": "2025-10-22T12:45:50.697572",
      "problem_text": "【複合違反】遊技機型式検定は3年有効違反と営業許可違反が同時に存在する場合、{theme_name}違反の方が重大である。",
      "correct_answer": "×",
      "explanation": "営業許可違反の方が営業全体に関わるため、より重大。",
      "source_pdf": 1,
      "source_page": 0,
      "teaching_value": "このパターンは違反の重大度判定を学ぶ上で重要"
    },
    {
      "problem_id": 116,
      "theme_id": 1009,
      "theme_name": "遊技機型式検定は3年有効",
      "pattern_id": 8,
      "pattern_name": "数値正確性",
      "difficulty": "★",
      "problem_type": "true_false",
      "format": "○×",
      "generated_at": "2025-10-22T12:45:50.697578",
      "problem_text": "【数値】遊技機型式検定は3年有効に関する具体的な期限・数値は講習テキストに明記されている。",
      "correct_answer": "○",
      "explanation": "はじめに\n\nばちんこ営業は、それが適正に営まれれば、「適度」に射幸心を\n満たす、国民に身近で手軽で健全な大衆娯楽を提供する営業です。\nパチンコ営業が、このように健金な大抄事楽を提供する産業として\n社会前役割を果たしていくたぬめには、その営業に用いられる遊技機\nが、客の射幸心を過度に詞るととのない、「適度] に射率心を満足\nさせるものであることが必要不可欠です。\n\nこのため、風俗泊業等の規制及び業務に具体的な数値が記載されている。",
      "source_pdf": 1,
      "source_page": 0,
      "teaching_value": "このパターンは細かい知識確認を学ぶ上で重要"
    },
    {
      "problem_id": 117,
      "theme_id": 1009,
      "theme_name": "遊技機型式検定は3年有効",
      "pattern_id": 9,
      "pattern_name": "理由理解",
      "difficulty": "★★★",
      "problem_type": "true_false",
      "format": "○×",
      "generated_at": "2025-10-22T12:45:50.697584",
      "problem_text": "【理由】遊技機型式検定は3年有効という規制が存在するのは、遊技業の健全化と不正防止のためである。",
      "correct_answer": "○",
      "explanation": "遊技機型式検定は3年有効は法制度設計の重要な目的に基づいている。",
      "source_pdf": 1,
      "source_page": 0,
      "teaching_value": "このパターンは法制度設計の理解を学ぶ上で重要"
    },
    {
      "problem_id": 118,
      "theme_id": 1009,
      "theme_name": "遊技機型式検定は3年有効",
      "pattern_id": 10,
      "pattern_name": "経験陥阱",
      "difficulty": "★★★",
      "problem_type": "true_false",
      "format": "○×",
      "generated_at": "2025-10-22T12:45:50.697591",
      "problem_text": "【経験陥阱】営業経験が長い者でも{theme_name}について誤解している場合がある。",
      "correct_answer": "○",
      "explanation": "遊技機型式検定は3年有効は実務経験と法律の乖離が生じやすい領域。",
      "source_pdf": 1,
      "source_page": 0,
      "teaching_value": "このパターンは知識修正能力を学ぶ上で重要"
    },
    {
      "problem_id": 119,
      "theme_id": 1009,
      "theme_name": "遊技機型式検定は3年有効",
      "pattern_id": 11,
      "pattern_name": "改正対応",
      "difficulty": "★★★",
      "problem_type": "true_false",
      "format": "○×",
      "generated_at": "2025-10-22T12:45:50.697598",
      "problem_text": "【改正対応】遊技機型式検定は3年有効に関する法改正があった場合、既存の許可も新規則が適用される。",
      "correct_answer": "×",
      "explanation": "既存許可は経過措置により保護されることが多い。",
      "source_pdf": 1,
      "source_page": 0,
      "teaching_value": "このパターンは法改正への対応を学ぶ上で重要"
    },
    {
      "problem_id": 120,
      "theme_id": 1009,
      "theme_name": "遊技機型式検定は3年有効",
      "pattern_id": 12,
      "pattern_name": "複合応用",
      "difficulty": "★★★★",
      "problem_type": "true_false",
      "format": "○×",
      "generated_at": "2025-10-22T12:45:50.697604",
      "problem_text": "【複合応用】遊技機型式検定は3年有効を含む複雑なシナリオでは、全ての条件を総合的に判断する必要がある。",
      "correct_answer": "○",
      "explanation": "遊技機型式検定は3年有効単独ではなく、複数要素を統合した判定が要求される。",
      "source_pdf": 1,
      "source_page": 0,
      "teaching_value": "このパターンは複数要素の統合判定を学ぶ上で重要"
    },
    {
      "problem_id": 121,
      "theme_id": 1010,
      "theme_name": "型式検定更新申請のタイミング",
      "pattern_id": 1,
      "pattern_name": "基本知識",
      "difficulty": "★",
      "problem_type": "true_false",
      "format": "○×",
      "generated_at": "2025-10-22T12:45:50.697611",
      "problem_text": "【基本知識】型式検定更新申請のタイミングについて述べている。",
      "correct_answer": "○",
      "explanation": "はじめに\n\nばちんこ営業は、それが適正に営まれれば、「適度」に射幸心を\n満たす、国民に身近で手軽で健全な大衆娯楽を提供する営業です。\nパチンコ営業が、このように健金な大抄事楽を提供する産業として\n社会前役割を果たしていくたぬめには、その営業に用いられる遊技機\nが、客の射幸心を過度に詞るととのない、「適度] に射率心を満足\nさせるものであることが必要不可欠です。\n\nこのため、風俗泊業等の規制及び業務から、型式検定更新申請のタイミングは正しい。",
      "source_pdf": 1,
      "source_page": 0,
      "teaching_value": "このパターンは基本的な法律事実を学ぶ上で重要"
    },
    {
      "problem_id": 122,
      "theme_id": 1010,
      "theme_name": "型式検定更新申請のタイミング",
      "pattern_id": 2,
      "pattern_name": "ひっかけ",
      "difficulty": "★★",
      "problem_type": "true_false",
      "format": "○×",
      "generated_at": "2025-10-22T12:45:50.697618",
      "problem_text": "【ひっかけ】型式検定更新申請のタイミングである場合、自動的に法的ステータスが変化する。",
      "correct_answer": "×",
      "explanation": "「自動的に」という表現は誤り。型式検定更新申請のタイミングは状況に応じた判断が必要。",
      "source_pdf": 1,
      "source_page": 0,
      "teaching_value": "このパターンは絶対表現への警戒を学ぶ上で重要"
    },
    {
      "problem_id": 123,
      "theme_id": 1010,
      "theme_name": "型式検定更新申請のタイミング",
      "pattern_id": 3,
      "pattern_name": "用語比較",
      "difficulty": "★★",
      "problem_type": "true_false",
      "format": "○×",
      "generated_at": "2025-10-22T12:45:50.697625",
      "problem_text": "【用語比較】型式検定更新申請のタイミングと営業許可は、同じ有効期限を持つ。",
      "correct_answer": "×",
      "explanation": "型式検定更新申請のタイミングと他の規制では有効期限が異なる。",
      "source_pdf": 1,
      "source_page": 0,
      "teaching_value": "このパターンは概念の区別を学ぶ上で重要"
    },
    {
      "problem_id": 124,
      "theme_id": 1010,
      "theme_name": "型式検定更新申請のタイミング",
      "pattern_id": 4,
      "pattern_name": "優先順位",
      "difficulty": "★★",
      "problem_type": "true_false",
      "format": "○×",
      "generated_at": "2025-10-22T12:45:50.697631",
      "problem_text": "【優先順位】型式検定更新申請のタイミングに関連する複数の対応が必要な場合、型式検定更新申請のタイミングの対応が優先される。",
      "correct_answer": "○",
      "explanation": "型式検定更新申請のタイミングは営業継続に直結するため、最優先で対応が必要。",
      "source_pdf": 1,
      "source_page": 0,
      "teaching_value": "このパターンは法律体系の理解を学ぶ上で重要"
    },
    {
      "problem_id": 125,
      "theme_id": 1010,
      "theme_name": "型式検定更新申請のタイミング",
      "pattern_id": 5,
      "pattern_name": "時系列理解",
      "difficulty": "★★★",
      "problem_type": "true_false",
      "format": "○×",
      "generated_at": "2025-10-22T12:45:50.697638",
      "problem_text": "【時系列】型式検定更新申請のタイミングの条件を満たしてから1年経過時点で、法的ステータスに変化がある。",
      "correct_answer": "○",
      "explanation": "時間経過により型式検定更新申請のタイミングに関する法的義務が生じることがある。",
      "source_pdf": 1,
      "source_page": 0,
      "teaching_value": "このパターンは時間経過による変化を学ぶ上で重要"
    },
    {
      "problem_id": 126,
      "theme_id": 1010,
      "theme_name": "型式検定更新申請のタイミング",
      "pattern_id": 6,
      "pattern_name": "シナリオ判定",
      "difficulty": "★★★",
      "problem_type": "true_false",
      "format": "○×",
      "generated_at": "2025-10-22T12:45:50.697644",
      "problem_text": "【シナリオ】営業者が型式検定更新申請のタイミングを含む状況で営業を継続することができるか。",
      "correct_answer": "○",
      "explanation": "型式検定更新申請のタイミングの具体的状況では、適切な対応により営業継続が可能。",
      "source_pdf": 1,
      "source_page": 0,
      "teaching_value": "このパターンは実務的判定を学ぶ上で重要"
    },
    {
      "problem_id": 127,
      "theme_id": 1010,
      "theme_name": "型式検定更新申請のタイミング",
      "pattern_id": 7,
      "pattern_name": "複合違反",
      "difficulty": "★★★",
      "problem_type": "true_false",
      "format": "○×",
      "generated_at": "2025-10-22T12:45:50.697651",
      "problem_text": "【複合違反】型式検定更新申請のタイミング違反と営業許可違反が同時に存在する場合、{theme_name}違反の方が重大である。",
      "correct_answer": "×",
      "explanation": "営業許可違反の方が営業全体に関わるため、より重大。",
      "source_pdf": 1,
      "source_page": 0,
      "teaching_value": "このパターンは違反の重大度判定を学ぶ上で重要"
    },
    {
      "problem_id": 128,
      "theme_id": 1010,
      "theme_name": "型式検定更新申請のタイミング",
      "pattern_id": 8,
      "pattern_name": "数値正確性",
      "difficulty": "★",
      "problem_type": "true_false",
      "format": "○×",
      "generated_at": "2025-10-22T12:45:50.697657",
      "problem_text": "【数値】型式検定更新申請のタイミングに関する具体的な期限・数値は講習テキストに明記されている。",
      "correct_answer": "○",
      "explanation": "はじめに\n\nばちんこ営業は、それが適正に営まれれば、「適度」に射幸心を\n満たす、国民に身近で手軽で健全な大衆娯楽を提供する営業です。\nパチンコ営業が、このように健金な大抄事楽を提供する産業として\n社会前役割を果たしていくたぬめには、その営業に用いられる遊技機\nが、客の射幸心を過度に詞るととのない、「適度] に射率心を満足\nさせるものであることが必要不可欠です。\n\nこのため、風俗泊業等の規制及び業務に具体的な数値が記載されている。",
      "source_pdf": 1,
      "source_page": 0,
      "teaching_value": "このパターンは細かい知識確認を学ぶ上で重要"
    },
    {
      "problem_id": 129,
      "theme_id": 1010,
      "theme_name": "型式検定更新申請のタイミング",
      "pattern_id": 9,
      "pattern_name": "理由理解",
      "difficulty": "★★★",
      "problem_type": "true_false",
      "format": "○×",
      "generated_at": "2025-10-22T12:45:50.697665",
      "problem_text": "【理由】型式検定更新申請のタイミングという規制が存在するのは、遊技業の健全化と不正防止のためである。",
      "correct_answer": "○",
      "explanation": "型式検定更新申請のタイミングは法制度設計の重要な目的に基づいている。",
      "source_pdf": 1,
      "source_page": 0,
      "teaching_value": "このパターンは法制度設計の理解を学ぶ上で重要"
    },
    {
      "problem_id": 130,
      "theme_id": 1010,
      "theme_name": "型式検定更新申請のタイミング",
      "pattern_id": 10,
      "pattern_name": "経験陥阱",
      "difficulty": "★★★",
      "problem_type": "true_false",
      "format": "○×",
      "generated_at": "2025-10-22T12:45:50.697671",
      "problem_text": "【経験陥阱】営業経験が長い者でも{theme_name}について誤解している場合がある。",
      "correct_answer": "○",
      "explanation": "型式検定更新申請のタイミングは実務経験と法律の乖離が生じやすい領域。",
      "source_pdf": 1,
      "source_page": 0,
      "teaching_value": "このパターンは知識修正能力を学ぶ上で重要"
    },
    {
      "problem_id": 131,
      "theme_id": 1010,
      "theme_name": "型式検定更新申請のタイミング",
      "pattern_id": 11,
      "pattern_name": "改正対応",
      "difficulty": "★★★",
      "problem_type": "true_false",
      "format": "○×",
      "generated_at": "2025-10-22T12:45:50.697678",
      "problem_text": "【改正対応】型式検定更新申請のタイミングに関する法改正があった場合、既存の許可も新規則が適用される。",
      "correct_answer": "×",
      "explanation": "既存許可は経過措置により保護されることが多い。",
      "source_pdf": 1,
      "source_page": 0,
      "teaching_value": "このパターンは法改正への対応を学ぶ上で重要"
    },
    {
      "problem_id": 132,
      "theme_id": 1010,
      "theme_name": "型式検定更新申請のタイミング",
      "pattern_id": 12,
      "pattern_name": "複合応用",
      "difficulty": "★★★★",
      "problem_type": "true_false",
      "format": "○×",
      "generated_at": "2025-10-22T12:45:50.697684",
      "problem_text": "【複合応用】型式検定更新申請のタイミングを含む複雑なシナリオでは、全ての条件を総合的に判断する必要がある。",
      "correct_answer": "○",
      "explanation": "型式検定更新申請のタイミング単独ではなく、複数要素を統合した判定が要求される。",
      "source_pdf": 1,
      "source_page": 0,
      "teaching_value": "このパターンは複数要素の統合判定を学ぶ上で重要"
    },
    {
      "problem_id": 133,
      "theme_id": 1011,
      "theme_name": "景品の種類制限",
      "pattern_id": 1,
      "pattern_name": "基本知識",
      "difficulty": "★",
      "problem_type": "true_false",
      "format": "○×",
      "generated_at": "2025-10-22T12:45:50.697691",
      "problem_text": "【基本知識】景品の種類制限について述べている。",
      "correct_answer": "○",
      "explanation": "はじめに\n\nばちんこ営業は、それが適正に営まれれば、「適度」に射幸心を\n満たす、国民に身近で手軽で健全な大衆娯楽を提供する営業です。\nパチンコ営業が、このように健金な大抄事楽を提供する産業として\n社会前役割を果たしていくたぬめには、その営業に用いられる遊技機\nが、客の射幸心を過度に詞るととのない、「適度] に射率心を満足\nさせるものであることが必要不可欠です。\n\nこのため、風俗泊業等の規制及び業務から、景品の種類制限は正しい。",
      "source_pdf": 1,
      "source_page": 0,
      "teaching_value": "このパターンは基本的な法律事実を学ぶ上で重要"
    },
    {
      "problem_id": 134,
      "theme_id": 1011,
      "theme_name": "景品の種類制限",
      "pattern_id": 2,
      "pattern_name": "ひっかけ",
      "difficulty": "★★",
      "problem_type": "true_false",
      "format": "○×",
      "generated_at": "2025-10-22T12:45:50.697698",
      "problem_text": "【ひっかけ】景品の種類制限である場合、自動的に法的ステータスが変化する。",
      "correct_answer": "×",
      "explanation": "「自動的に」という表現は誤り。景品の種類制限は状況に応じた判断が必要。",
      "source_pdf": 1,
      "source_page": 0,
      "teaching_value": "このパターンは絶対表現への警戒を学ぶ上で重要"
    },
    {
      "problem_id": 135,
      "theme_id": 1011,
      "theme_name": "景品の種類制限",
      "pattern_id": 3,
      "pattern_name": "用語比較",
      "difficulty": "★★",
      "problem_type": "true_false",
      "format": "○×",
      "generated_at": "2025-10-22T12:45:50.697704",
      "problem_text": "【用語比較】景品の種類制限と営業許可は、同じ有効期限を持つ。",
      "correct_answer": "×",
      "explanation": "景品の種類制限と他の規制では有効期限が異なる。",
      "source_pdf": 1,
      "source_page": 0,
      "teaching_value": "このパターンは概念の区別を学ぶ上で重要"
    },
    {
      "problem_id": 136,
      "theme_id": 1011,
      "theme_name": "景品の種類制限",
      "pattern_id": 4,
      "pattern_name": "優先順位",
      "difficulty": "★★",
      "problem_type": "true_false",
      "format": "○×",
      "generated_at": "2025-10-22T12:45:50.697711",
      "problem_text": "【優先順位】景品の種類制限に関連する複数の対応が必要な場合、景品の種類制限の対応が優先される。",
      "correct_answer": "○",
      "explanation": "景品の種類制限は営業継続に直結するため、最優先で対応が必要。",
      "source_pdf": 1,
      "source_page": 0,
      "teaching_value": "このパターンは法律体系の理解を学ぶ上で重要"
    },
    {
      "problem_id": 137,
      "theme_id": 1011,
      "theme_name": "景品の種類制限",
      "pattern_id": 5,
      "pattern_name": "時系列理解",
      "difficulty": "★★★",
      "problem_type": "true_false",
      "format": "○×",
      "generated_at": "2025-10-22T12:45:50.697720",
      "problem_text": "【時系列】景品の種類制限の条件を満たしてから1年経過時点で、法的ステータスに変化がある。",
      "correct_answer": "○",
      "explanation": "時間経過により景品の種類制限に関する法的義務が生じることがある。",
      "source_pdf": 1,
      "source_page": 0,
      "teaching_value": "このパターンは時間経過による変化を学ぶ上で重要"
    },
    {
      "problem_id": 138,
      "theme_id": 1011,
      "theme_name": "景品の種類制限",
      "pattern_id": 6,
      "pattern_name": "シナリオ判定",
      "difficulty": "★★★",
      "problem_type": "true_false",
      "format": "○×",
      "generated_at": "2025-10-22T12:45:50.697727",
      "problem_text": "【シナリオ】営業者が景品の種類制限を含む状況で営業を継続することができるか。",
      "correct_answer": "○",
      "explanation": "景品の種類制限の具体的状況では、適切な対応により営業継続が可能。",
      "source_pdf": 1,
      "source_page": 0,
      "teaching_value": "このパターンは実務的判定を学ぶ上で重要"
    },
    {
      "problem_id": 139,
      "theme_id": 1011,
      "theme_name": "景品の種類制限",
      "pattern_id": 7,
      "pattern_name": "複合違反",
      "difficulty": "★★★",
      "problem_type": "true_false",
      "format": "○×",
      "generated_at": "2025-10-22T12:45:50.697735",
      "problem_text": "【複合違反】景品の種類制限違反と営業許可違反が同時に存在する場合、{theme_name}違反の方が重大である。",
      "correct_answer": "×",
      "explanation": "営業許可違反の方が営業全体に関わるため、より重大。",
      "source_pdf": 1,
      "source_page": 0,
      "teaching_value": "このパターンは違反の重大度判定を学ぶ上で重要"
    },
    {
      "problem_id": 140,
      "theme_id": 1011,
      "theme_name": "景品の種類制限",
      "pattern_id": 8,
      "pattern_name": "数値正確性",
      "difficulty": "★",
      "problem_type": "true_false",
      "format": "○×",
      "generated_at": "2025-10-22T12:45:50.697742",
      "problem_text": "【数値】景品の種類制限に関する具体的な期限・数値は講習テキストに明記されている。",
      "correct_answer": "○",
      "explanation": "はじめに\n\nばちんこ営業は、それが適正に営まれれば、「適度」に射幸心を\n満たす、国民に身近で手軽で健全な大衆娯楽を提供する営業です。\nパチンコ営業が、このように健金な大抄事楽を提供する産業として\n社会前役割を果たしていくたぬめには、その営業に用いられる遊技機\nが、客の射幸心を過度に詞るととのない、「適度] に射率心を満足\nさせるものであることが必要不可欠です。\n\nこのため、風俗泊業等の規制及び業務に具体的な数値が記載されている。",
      "source_pdf": 1,
      "source_page": 0,
      "teaching_value": "このパターンは細かい知識確認を学ぶ上で重要"
    },
    {
      "problem_id": 141,
      "theme_id": 1011,
      "theme_name": "景品の種類制限",
      "pattern_id": 9,
      "pattern_name": "理由理解",
      "difficulty": "★★★",
      "problem_type": "true_false",
      "format": "○×",
      "generated_at": "2025-10-22T12:45:50.697748",
      "problem_text": "【理由】景品の種類制限という規制が存在するのは、遊技業の健全化と不正防止のためである。",
      "correct_answer": "○",
      "explanation": "景品の種類制限は法制度設計の重要な目的に基づいている。",
      "source_pdf": 1,
      "source_page": 0,
      "teaching_value": "このパターンは法制度設計の理解を学ぶ上で重要"
    },
    {
      "problem_id": 142,
      "theme_id": 1011,
      "theme_name": "景品の種類制限",
      "pattern_id": 10,
      "pattern_name": "経験陥阱",
      "difficulty": "★★★",
      "problem_type": "true_false",
      "format": "○×",
      "generated_at": "2025-10-22T12:45:50.697756",
      "problem_text": "【経験陥阱】営業経験が長い者でも{theme_name}について誤解している場合がある。",
      "correct_answer": "○",
      "explanation": "景品の種類制限は実務経験と法律の乖離が生じやすい領域。",
      "source_pdf": 1,
      "source_page": 0,
      "teaching_value": "このパターンは知識修正能力を学ぶ上で重要"
    },
    {
      "problem_id": 143,
      "theme_id": 1011,
      "theme_name": "景品の種類制限",
      "pattern_id": 11,
      "pattern_name": "改正対応",
      "difficulty": "★★★",
      "problem_type": "true_false",
      "format": "○×",
      "generated_at": "2025-10-22T12:45:50.697762",
      "problem_text": "【改正対応】景品の種類制限に関する法改正があった場合、既存の許可も新規則が適用される。",
      "correct_answer": "×",
      "explanation": "既存許可は経過措置により保護されることが多い。",
      "source_pdf": 1,
      "source_page": 0,
      "teaching_value": "このパターンは法改正への対応を学ぶ上で重要"
    },
    {
      "problem_id": 144,
      "theme_id": 1011,
      "theme_name": "景品の種類制限",
      "pattern_id": 12,
      "pattern_name": "複合応用",
      "difficulty": "★★★★",
      "problem_type": "true_false",
      "format": "○×",
      "generated_at": "2025-10-22T12:45:50.697769",
      "problem_text": "【複合応用】景品の種類制限を含む複雑なシナリオでは、全ての条件を総合的に判断する必要がある。",
      "correct_answer": "○",
      "explanation": "景品の種類制限単独ではなく、複数要素を統合した判定が要求される。",
      "source_pdf": 1,
      "source_page": 0,
      "teaching_value": "このパターンは複数要素の統合判定を学ぶ上で重要"
    }
  ]
}