[
  {
    "text": "338 資料 六                                                              中古施技科流通健全化要絹 339\n\nこの要綱は、令和元年5 月 1 日から施行する。                                         別記様式第1号\n昭 則                                                                                                        -\nこの要綱は、令和3年4月1日から施行する。                                                          保         証         書\n遇 則                                                      下記遊技機について持、点検・確認することにより、風俗党\nこの要綱は、令和 3年10月1 日から施行する。                      業等の規制及び業務の適正化等に関する法律筑20条第4 項の検\n際 則                                       定を受けた型式に属するものであることを保証します.\n\nこの要綱は、令和4 年12月 1 日から施行する。\nパ   員                                                  信和   年   月    月\n公安委員会 騰\n\n会安訟負会が雪める者の兵名又は名称、住所及び生年月\n\nG) 所属保守管理業者千の氏名又は名称及び住所\n全) 符例風俗営業者の氏名文は名称及び住所\n\n記\n剖    回|    中本補移動",
    "pdf_index": 3,
    "page_number": 31,
    "source": "lecture_materials"
  },
  {
    "text": " ・ 簡定     陸扱騰の往瑞\nEEEE色\n統倍義所の生和\nEDP\n陣二者|                  還式寺山天\n較 式 逢\n険定年月日   令和   年   月   昌   |柄 証 番 中\n時3 護ちんこ直和  衝技毅番等 障半区の要秋号間  主甘板番号等\nも          こ        ーー              =\nme  本人等 回層) |本人和呈和(人人部| 主基板秋号等\n\n| ごの時類は、作成した日から中古引移動は 0 日以内、証は 0日以内に提出しなければならない。\n\n備\n1 作成震和は、氏和名を記載す\n2 不要の文字統、横線で消す     料\n8 (1)朋び(せ)は、公宏員会が放技機の点栓及び取扱いを適正区行うに足りる角力を\n有すると認める者のうち、遊披北の誰定及び型式の松定等団する規則第 1 条第3項第\n3 号ロ(2)及び(8)を意味するので、譜当しない揃を消した上、これを記載すること\n。 4 「中古機移動」は、風俗営業の営業所に設置されたことのある導技機を営業\nすることを意味する。\n5 「設軒先』の括は、売買約等の締語内容全沿って記載すること。\n6 所定の棚に衣温し得ないときは、別交に記載の上、これを深付すること。\n7 用病の大きさは、日本睡業志格A4 とする。",
    "pdf_index": 3,
    "page_number": 31,
    "source": "lecture_materials"
  },
  {
    "text": "きき\n較\n由\n内\n寺\n思\n世\n回\n\n340 資 狼 訪\n\n者\n表\n電\n瑞\nき\n撮 |息\n下\n電|齋\n玩 |交\n 要|朱\n斉藤\n往 と\n人 上                EE\n呈 |時\n3 韻                TEN\n京 |更                ES\n層                SI |吉\n*                前\n丘 性                埋|吾|尼\n由 内                EE\n民 |                組 利 時\n高                 ーー -\n\n1               上\n|              陣\n3\nBE\n色香\n共 型番\n|\nり 拉ー\nk生\n3\n               還\n-                  3\nに 前               宗1。|避\n|長               e| |\n耳 |海               TS\n挫                MM\n江                EE\n本\n半 |押               訓 理東\n机",
    "pdf_index": 3,
    "page_number": 32,
    "source": "lecture_materials"
  },
  {
    "text": "342 資 次 編                                                                中古旗披各取扱業務実衝要領 343\n\n別記様式第2号\n\n〇中古遊技機取扱業務実施要領\n\n令和  年  月  上\n\n主 基 板 保 証書\n\nMa\n\n最改正 令和5年8月1日\n(登録独) (和合)\n\n殿\n-                       。 (目的)\nPP                         第1条 この要領は、中古遊披狂流通健全化奨納 (以下「綱」という。) 第22\n人 導                           条に藩づき、中古施技機 (以下「中古機」 という。) の取扱い染務に関し、具\n体多な実施肖領を定め、もってその業務の剖正化を図ることを目的とする。\n下記2の遊技機の新主基板は、            公安委員会の稚定を受けた型式に                    (中類の打刻)\n属する遊技後の主基板であることを保証します。                                 テ\n_                       第2条 取角主任者又は取扱管理者が作成し、所届する登録販売染者又は特例党\n1 交               時                               :.業者に提出した保証豆、当吉中古機の検定通知番 (甲) の写しとともに、こ\n本 拓 、宝                                       れを所管する全商協傘下の地区どとの施技和商協同組合 (以下「地区誠商」\n阿       大              ーー                           --という。) 又は回肌施曽た是靖",
    "pdf_index": 3,
    "page_number": 33,
    "source": "lecture_materials"
  },
  {
    "text": "し、中古機流通協議会印の打刻を受けなければ\n検 齋 番号|     ー                                  なちない (以下「打刻申庶] という。)。この場合において、特例党楽者人仲介\n検定 持 月 日                                       。 する地区工商組合員又は回肌遊商組合員 (以下「促介組合員] という。) を純\n\n上記 1の人産技機の型式に展する主基板                                                                    由して地区遊商又は回胴遊商に書類を提出する。\n\nに人 信和の抽和\nak | 本人上和号 (財) |          新主匠和呈                   皇基板和号            8                          (得去遊技指明細書の提出及び保管\n\nIM\n\n1                                            遊技機を撤去するときは、変\n因       9      に           胃絹が記載された変更店、\nー        _-                         M     細番 ). _(古) .(骨様基第9) 作和見今に\n\n2  -管理者は、 串村の移動等をする場合は、 取扱主任者又は取扱管理者を経由\nしでて、当該遊技機に係る前刺の変更承欠申請変更届出撤去遊技機明細療\n『(副) の写しを地区遊商駐は回胴遊貢に提出しなければならない。\n\neiel lalgl*lels\n1\n|\n\n|\n\n9. 概半先 ュ                                (中古必技機確認の作成)\nき 介 四         ",
    "pdf_index": 3,
    "page_number": 33,
    "source": "lecture_materials"
  },
  {
    "text": "                      第4条 管理者は、中古機の移動等をする場合は、当訪中古機が正覚であること\nを確認し、中古遊技機確認半 (別記様式第 2 ) を作成した上で、取扱主任\n\n池) この香和は、作沙した日から 0日以内に失出しなければならない。\n\n信和 1 計の光は、槍珠で靖すこ             _                -           又は取扱管理者を経由して、これを地区遊商又は回胴遊商た提軸しなければ\nら. 対定の穫に良幸し得ない』 HH 別絶に記載の上、これを浅付すること。\n3 用交の大ききは、昌本音格人4とすること。                                      ならない。\n(点検確認の実施)\n第5条 要綱第11条第1 項に現定する基栓確認は、中古ばちんこ産技機等 (回肌\n式を除く。 以下同じ。) 不検確認受渡書 (別記様式第 3 与) 又は中古同胴式遊",
    "pdf_index": 3,
    "page_number": 33,
    "source": "lecture_materials"
  },
  {
    "text": "344 資 装 引\n\n技機点槍認受渡書 (別記様式第4号) (以下「点確受渡書} という。) K |\n\n示さきれた項目について行う。\n\n2 取扱主征考又は取扱管理者は、当訪中古機が菅業所に設置きれたとまき、点概\n確認受渡書に示された当訪中十機に関わる全項目について、 異常等の有無を記\n換し、これに記録する。\n\n(中古機の保全等)\n\n第6朱 取扱玉任者又は取扱管理者は、前条第 1 項に規定する点検確認の結果、\n異常が認められなかったときは、ばち んと次の場合は全商陣が、   図胴区の場合\nな回員遊商がそれぞれ定めた方法により型式の保全措置をとる。\n\n(保管・納品確認書の作成)\n\n第7梨 取扱玉\n後に保管・納品肉認療(別記様式第5号) に所定の事項を記入する。\n\n2 管理者は、保管・綱品確認書に中古機を受領した際の綱品菜者及び受領昌時\nを記入し、当談申吾機の現式の保人状態を確認の結果、暴常がかない場合には氏\n名を本表する。\n\n3 型式の保全振置を燃除するのは、取扱主任基駐は取扱管理者もしくは管理閉 …:\n\n(当譜保会描代をとった取扱主任書駐は取扱管理者の丁解を得た者に限る。)\n\nとし、当設保例挫加を解除した者は、保管・癌確認書に日時を記入し、民名\n\nを記載する。\n\n4 取扱主任者又は取扱管理者は、完成した保管・績品確認書を、所属する登録\n販売者又は特例営業者及び伸介組合員を経由して (書頻提出の綴由要件は以\n同じ。)、地区施商又は回胴遊商に失出する。\n\n(点検確認受渡書の作成)\n\n第8条 管理洗は、也扱主任涯又は取扱管理者による第5条第2 項に規定する点\n栓共認\nを記載し、当該遊技機を受領する。\n\n2 取扱主任者又は取扱管理者は、点検益認受渡愉 (正) (出) を作成し、(博)\nは営業所渡し、(正) は地区遊商又は回胴遊黄に提出しなければならない。\n\n(確認証紙の貼付)\n第9条",
    "pdf_index": 3,
    "page_number": 34,
    "source": "lecture_materials"
  },
  {
    "text": " 取扱主任者又は取扱管理者は、第5条第2項による県検准認の千昌、暴\n\n常が認められなかったときせは、当該中古機1台ごとに、ばちんこ侍の場合は郊\n\n技盤の棒番号付近もしくはそれに準ずる位置に、較胴式の場合は人筐体部内面に\n確認証紙(中古用) を貼付する。\n\n2 取扱主任者及び取扱管理考は、確認証紙 (中古用) を破損叉は稔失したとき\nは、欠行革の地区遊商又は則肌遊商に対し、近やかに彼抽した確認証紙 (中青\n\n者又は取表管理者は、前休に規定する型式の保全措軒をとった :\n\nに立会い確認し、 異常がないととを認めたときは点検槍朗受渡若氏争.:\n\n中古遊技秋取扱薬実施要領 345\n\n用) を返約し、又は紛失した旨を報告して再発行を申請しなければならない。\n(管理者業務の代行)\n第10祭 営業所に所属する遊技機取扱主任者 (以下「ホール取扱主任者! とい\n^ う) は、管理者が不研たかるときは。管理首の指示を受けて、 第4休。 第7.\n殺第 項及び第き項並びに第8休第1 項で守有ぬられている管理者@沙務を代行\nすることができる。.\n2 ホール取扱主任者は、前項の業務を行うに当たり、関係者から遊技和取扱\n任者本の提示を求められたときは、これを提示しなければならない。\n附 則\nこの要領は、要綱の施行の日から施行する。\n\n附則\n(施行期日)\n1 この要領は、平成17年2 月 1 日から施行する。\n(手数料等\n2 特例営業閉は、第2 条の規定による持鹿中庶をする際、交の各号の手数料等\n(消費税別) を地区進商又は回胴放商に納付するものとする。\n(1) 打刻等手数料 1機械6000円\n3) 確認剖抵代      1攻 500幅\n内 則\nこの要領は、平成22年 6 月 1 日から施行する。\n診 則\nこの要領は、平成27年2 月 1 日から旅行する。\n附 則\nこの要領は、平成27年12月 1 是か",
    "pdf_index": 3,
    "page_number": 34,
    "source": "lecture_materials"
  },
  {
    "text": "ら施行する。\n内 則\nこの要領は、平成29年12月25日から施行する。\n附 則\nこの要領は、令和元年5月1 日から施行する。\n花 則\nこの要領は、令和元年 6 月 1 日から施行する。\n時 則\nこの要領は、令和2年3月 ] 日から施行する。\n内 則\nとの要領は、令和 3 年10月1 日から施行する。\n除 則",
    "pdf_index": 3,
    "page_number": 34,
    "source": "lecture_materials"
  },
  {
    "text": "346 資料 訪                                                          中古放技機了扱業務実施四領 347\n\n(施行期日)\n\n1 この要領は、令和 4 年12月 1 日から施行する。\n(経過描置)\n\n2 この要領による改正前の別記様式については、この要領による改正後の別記\n様式に関わらず、令和5 年12月31日までの間、なおこれを使用することができ\nる。\n\n附則                            :\nこの要領は、令和5年9月1日から次行する。 (別記様式第3号及び別記様式\n\n際財年月日 台表\n\n第4号の変夏)               gg\n東上四\n時\nきす |\"  上\n回 時   上\ndl 特\n拓    民|\n選\n\n本体製迄稚号 (回避部)\n\n|\n軸\n引\nき\n析\n拓\n対\n肖\n羊\n由\n肖\nロ\n刷\n\nで清してくだきい、\n\nロロ ぱちん\n本者(EX)を、演技乏の入天・没吉に全う人店諾又は変屋由の果に也弥天に手出し、返却きれた(は営甘所にて猿符しでください。\n\n二不吉の",
    "pdf_index": 3,
    "page_number": 35,
    "source": "lecture_materials"
  },
  {
    "text": "348 資料 訪                                                            中古遊技機取扱沼実施胃領 349\n別記様式第2号\n\n中古遊技機確認書\n\n直語番号\n\n着\n内\n古\n 、| |、|、|、|、\n回回回回回\n                                 EE    PS\n則                               本人(回朋陣) | 本全休\n時\nス   民\n筐 1]\\*     』 |\n上開国\n間開|\n量 |生\n臣 |     3圭二\n問   同       旨間\n前       涯昌\n選       名 半\n局          還                              の人はて才衣ましてい光琴でおにときた\n久                                                | 上際の外交は全て正常であることを細める\n          月                              上弄の間近はない\nM         和                              の肖抽に凍作の不了人をり付けでいない\n捕          半 肖                            深項目c、において「いいえ」の現合ほその内容を記隊してください\n中\n由          国人\n絡         誠人\n| 憶\n回届                    放員の確認 ※枕時において、確認をして加をつけてください\n肖                               口上紀聞愉対する欠償はありよせん\n四\n回\n東            装民\n内           筑l\n沸    で]",
    "pdf_index": 3,
    "page_number": 36,
    "source": "lecture_materials"
  },
  {
    "text": "W| 各剛                    !    の本衝で捕してくだきい\n3   吉|W|守|                  |         2 所旋の剛に形し衝ないときは、別託に記工の上\n居   細避|東湖\n富    央| を   家        1_.",
    "pdf_index": 3,
    "page_number": 36,
    "source": "lecture_materials"
  },
  {
    "text": "350 資 料 編\n\n中古店技租取扱業務実施領 351\n\n別記様世第2号 別紙 (中証遊技機巡認番用)                        別記様式第3号\n遊技機の製造番号                                                中古ばちんこ遊披機等点検確認受渡書(正)\nばちんと等|    作投番号       導抽雅光番号          」              ー\n合交| 本休人知号 (部) | 浴和人和号 (入体部)   MM      MM           隊和上示間/和営守|              町草午販区付需\n1                                                            孤提作者/取扱和理                   還地人寿才番別 |\n拓検日| 信和                EE\n章 式                                   3\n|角| 池番     BE     人6符号 | 稼紅生 。 放衝梨|\n1\n四\n3\n加\n5\nR\n               |\nき\ns\n19\n軸\n四\n\n次のの、訟当する玉朋について沙\n仙和が、訟交する須大\n\n製千番号等の点失9\n\n陵きのび和号の上人                   1 2当の設千がないか\n\n陸生のが芝天上                 16 |人TH:本の江人に共和はないか\n\n上なの:Hs和生の                   17 1に大光は邊人の紀者がないか\n等の県   上                             に     (の,    是\n\n訴ケータに肛状江公は日3き】たこめ           16 1レッテャンサ",
    "pdf_index": 3,
    "page_number": 37,
    "source": "lecture_materials"
  },
  {
    "text": "ナーの\n\nに形汰は褒がないか                FE EETTRRSあ\n\nERRTEF3          20 了ほwoft\n\n4い、委「上有殿』に和共なEを間し、\n\nクタービ形民衛折り波符がないか\nに光り半基がないか\n避寺上栓妥は、 しン17の項目について循5\n\n調和\n上昌遊革擬を点検項目に基づき確認し、暴常がないことを認め、受領しました。\n\nュ、ににににににににににににににトトにににトトトトトトトドトドににトトドドトトドドトト\n\nにきににGSES EN ESES RSESES ESESESESESESESENERESESESESEにSESKに\n\n憶杯諾の刻克|\n\n半 業 所\n\nの 名 疾\n\n詳落の岳\n\n名叉は外交\n\n信理 者\nEE                            人生\n\n代理壮笑号\n\npK徹語シートAACO拉明(地了データ全島た場人にする、\n口 旧人村人条シート区び用扱明和(    きる)を受伯しましな」\n\n2.受価し人理者駐はホール責住半は氏名を記載し、管者番号双は必統痢和おを外罰\n3 所定め家配江し付いとき、別交に般の上、ごれを本付するに",
    "pdf_index": 3,
    "page_number": 37,
    "source": "lecture_materials"
  },
  {
    "text": "352 資 料 語                                                             中古遊披機取扱務実導要領 353\n\n別記様式第3号\n\n|                      中古ばちんこ人遊披機等点検確認受濾貫(財)                             遊投機の製追番号等\nE                        座角販売楽者/符例営業者                                              町刻蘭類変付番号|                                                                         洪授稿番号             放流比の枠番号           王基板番号             確陣証紙番号         記栓結果\n|          陣有信者/取投各理独|                    匠抜主公者番 |\n人NH|  S衝                                                                                          |\nsg\nEGGE3\n_1\n 区の天目のち、拓当する下選ついて応寺硫陣を行い、 上記「京格寺果」細に臣常がないときは〇を憧入し、\n東間があるときは、暑当叶宏昌番号あ窟入する。\n(の占和項\n(計状紅番号の徹衣藤ば客号明の点愉                        5 【世パッタに思牧の時着がだいか\n|放拉修の神番号の太当ザ番号県の点科                     6 膨挟串又は拓記の形状に其常はないか\n番号の確認が臣号手の上柱\nの点検項\n|計",
    "pdf_index": 3,
    "page_number": 38,
    "source": "lecture_materials"
  },
  {
    "text": "基概ケースに秦羽典生又は便封まれたこん随志ないか\n|計基枢に所状四信叉は虹物の閉玲ポないか\n|際出基又は李紀算馬ダースに形状典入又は衣されたこん|涼汰ないか\n|際山基弧又は析出御基字形状財淀務は内物の寺落人はかいか\nにふの表洪叉は打誰況た敵室はないか\n1の」\nTi多久がないか\n中紅遇板に形状四党又は殿村装着がないか\n外部昌子板に也状異演叉は時塊角着がないか(※)\n|半人代出半科本子需形准内深は還物の湊半交ないか      25 1 べての第位所の京柱\n「キタターに月凌介叉は系物の装着がないがか>               26 1メピビーカーの作動秩\n                                                  罰E3T2ZZ279iCT\n                                              と\n台生       回\n設囲業所の所在地|\n賀慎業所の名台|\n                                                                                                                       較EEEEOGEEEEGEI\n\n管理者番号\n玉生な\nくき記隊シートび取哲明内(則子テデー合わ)を和軍した電信する。\n\n上宙技午9く科引ツート誠撤説明宙(代子データ合わ)な和信しました。\n\n全邊環1は要有で消すこと\n 肝全した穫理者玉はホール友投許着は氏を訴し、幣理者和号双は遊技析主人番号を二入すること。\n3所定の間に械し但ないときは、別誠に本枚の上上、とれを訟行すること。",
    "pdf_index": 3,
    "page_number": 38,
    "source": "lecture_materials"
  },
  {
    "text": "854 資 料 編                                                           中古施機取扱業聞実放要叙 355\n\n別記様式第4号                                                                                                                                      別記様式第4号\n中古回胴式遊技機点検確認愛減書(正)                                   中古回胴式遊技機点検確認受洪書(副)\n\n際碗朱者/和人党委                     人番有       画           IEEEZOや                    EE\n投寺作者/刺抽各理者|                      陣長作着番史         ]           怪人錠/也板償理導|                      攻旦生痢番和\n長栓| 全邊   回   回   上 |避造染者                          上共入| sm   年   月   貞操者\n\n型式                                   4                   EE|                                  人 数\n\n本体記生                                           EE            間靖        間\n\nし半    遍 王       伺 作 衣      MM     Mk間較 Med          |    本       ",
    "pdf_index": 3,
    "page_number": 39,
    "source": "lecture_materials"
  },
  {
    "text": "証      株     人人 上 時\n\nュ                                                             H\n\n四                                                    [3\n\n日                                                         3本\n\nロ                                                            呈\n\nR                                                            回\n\ns                                                             H\n\nH                                                             ?\n\n*                                                             日\n\n5\n\n内                                                             四\n\n1                                                             9\n\n四                                                             四\n\n深み順目のうち、話当する項目について京穫地認を和有や、記「検梨糧に避剖92いESTES到錯入し、\n\n内のうち、入するについて失いて上TREEESBO",
    "pdf_index": 3,
    "page_number": 39,
    "source": "lecture_materials"
  },
  {
    "text": "補し、\n\nかめは、和泊る生を還人する                                                                               20あるあきは、放する正和大する\n\nNB                 民       順目xnEHgRRagrcuiW9め\n055光(EZTGD2ESOE27IS           |和枝ケースに泊び全和3ルたこん丈がなか\n\nメタ0ル第基板の点失項目us- vgrxpEBeehxtWtck\nの破計及び番号理の点杭              17 ドレダル培了芝湖ケーメに天届攻区び誠計れたこん際人ないか\n|休押六番時(午休部)の位窟藤び委号妖の点検                    ツル開基本に下穫代党(ば旧暫の時着がないか                                      [を作遇着番号 (全体部)の磁認及び需号配の点              1ダル纏匠に接居器療獲物の誌共がないか\n上は半和王きせ克評各証の貞衝 ru     たかの背汰び玖にはな 】                            守革上普号の催及び符号履の点拍                        19 |メデル投基に拘人たの形江及び紹状た具生ないか\nPS\n\n孝品の点検融目(マートパテにる)\n\n(の夫区(スマートパチ2\n\n寺誠ケースの人的下に前科さたこんいが、\n\n5\n] [29紀和の生か                                                        股250GNSBESCWD2277EKMBEDSHHF2OEIOD2RHECONK\n琴酸ケースに形3引芝到が朋伯されたとん対がかいか           の        ",
    "pdf_index": 3,
    "page_number": 39,
    "source": "lecture_materials"
  },
  {
    "text": "                                                                         基本麗作の点検項目\n誠人の交かいか                ツルギンクターの作有38                                                                               2グルセレクターの作和6            ー\n党せないか                                                                                                             22回則回村流思の信動全\n間人の                                            RC                             因 還SHeedt(82和3\nど CE大び人人の人がないか             上湾等の動胡膨双はメダル破示箕納詳                        崩基仮形拓大党太上物の絡着がないみ           124 箇才等め作過確謀又なメダル映訴示居の浴認\n\n地板に大信人知ら紅導がないか            |定更和の人                                      人引に有汰及で物の失がか          205光層の作\n|にキクテーに月慌供選大び暴貼の橋導がないか           |ビールーの作呈強褒.                                  ビネクターに形状異和及び暴物の装療がないか         26 |スピーカーの作画中              ",
    "pdf_index": 3,
    "page_number": 39,
    "source": "lecture_materials"
  },
  {
    "text": "   ゴ\nに天失及びが計物の務がないか\n\n3 |符竹ジンプの応条記                                  _\n\nその他\n\n開 同iNETHI2のHTOHP72YCP5D\n店253\n\nMRックス形状常基区の半送ばないか\n直面了が側面に形汰座長び負約の基落はないか                   |入邊による投和閣枝メダル、下技球のはメアル委朱刻の泊\n外交子板に形杖舘決の丘着がないか(38                      隅投入の時\n|はダルヤレクタード形状内和護物の二落はないか (5)\n\nし                                       遇TWINEWPPTITWT                                           はMDTGDHRKYRTWRTTWWW拉\n                           ※※管理誠記入栖                                                                                                                                              ※飼理考記入抽\nも                                         上記遊技機を点検項目に基づき確認し、異堂がないことを認め、受額しました。                                                        上記庶技※点栓項目に基づき科認し、異常がないことを認め、受領しました。\n1                                      EE                   ",
    "pdf_index": 3,
    "page_number": 39,
    "source": "lecture_materials"
  },
  {
    "text": "     回               回                』                昌                         回2                                                                                              人               を                』               日                         還有\n                           叶療所め名衝                                                                                                                                                営業所の名称|\n記在電                                                                                                                                 」                                   所在地\n1                    ES |                  Eee",
    "pdf_index": 3,
    "page_number": 39,
    "source": "lecture_materials"
  },
  {
    "text": "356 資料 編                                                            中古遊技機取扱務実施要領 357\n\n列記様式第4号 別紙 (同員式放技機用)\n\n遊技機の抽造番号等                 9           保管・納品確認書\n四史           8 ET            Ws                     林寺者/特例近拓                       還EE2ES8\nき        代休 吾    1                                   取湊人放/ 取表管理                  取妥主任導秋多\nEE         サディーシール癌人\nトー\n管理者請品和認\n上記進技機を次の各号に基づき確認し、下記納品業者より受領しました。\nの上記才技のセキュサティーシール邊号光正でめること。\n@上記才朱欄の包六・セキリティジールが開講されていないこと、また前刑された旗跡がないこと。\nEE                   表人日時 | 年 月 時\n]                           絢                      腔促日時 |令打 年 月 昌 時\nEE                       EEEEEEEE還還\n生理 者                                      天寿\n取F                              PTY\n針                間人作者 淡和なホール選抽吉住が半する才合は、由人六は骨管理者の了人4を香6こた\n|記の記人期                                           ",
    "pdf_index": 3,
    "page_number": 40,
    "source": "lecture_materials"
  },
  {
    "text": "                                                     且詩日時| 信和 年 月\n同 民所の名稲                                                                                                                        取在任者/電拉乏者\nER                                                                   NE作\n\n 1 不所の丈字和本護で消すこと\n-季者ははポール人基注び間商人者は氏名あ補し管理又は人村投人吉半おを記入すること=",
    "pdf_index": 3,
    "page_number": 40,
    "source": "lecture_materials"
  }
]