{
  "metadata": {
    "version": "1.0",
    "created_date": "2025-11-06",
    "source": ["wind_eikyo_law", "lecture_guide"],
    "total_count": 46,
    "description": "試験問題生成用の複合語辞書"
  },
  "compound_words": [
    {
      "id": 1,
      "word": "営業許可",
      "category": "law_concepts",
      "importance": 5,
      "frequency": "very_high",
      "context": "遊技場営業に必要な都道府県公安委員会からの許可",
      "must_not_decompose": true
    },
    {
      "id": 2,
      "word": "型式検定",
      "category": "law_concepts",
      "importance": 5,
      "frequency": "very_high",
      "context": "遊技機の規格合致性を確認する制度",
      "must_not_decompose": true
    },
    {
      "id": 3,
      "word": "営業禁止",
      "category": "law_concepts",
      "importance": 4,
      "frequency": "high",
      "context": "営業が禁止される時間帯や区域",
      "must_not_decompose": true
    },
    {
      "id": 4,
      "word": "営業停止",
      "category": "law_concepts",
      "importance": 4,
      "frequency": "high",
      "context": "違反時に発令される行政処分",
      "must_not_decompose": true
    },
    {
      "id": 5,
      "word": "不正改造",
      "category": "law_concepts",
      "importance": 5,
      "frequency": "very_high",
      "context": "遊技機の違法な改造行為",
      "must_not_decompose": true
    },
    {
      "id": 6,
      "word": "遊技機",
      "category": "equipment",
      "importance": 5,
      "frequency": "very_high",
      "context": "パチンコ・パチスロなどの遊技用機械",
      "must_not_decompose": true
    },
    {
      "id": 7,
      "word": "営業所",
      "category": "facility",
      "importance": 4,
      "frequency": "high",
      "context": "遊技場が営業する施設",
      "must_not_decompose": true
    },
    {
      "id": 8,
      "word": "営業者",
      "category": "actor",
      "importance": 4,
      "frequency": "high",
      "context": "営業許可を得て遊技場を経営する者",
      "must_not_decompose": true
    },
    {
      "id": 9,
      "word": "景品",
      "category": "law_concepts",
      "importance": 4,
      "frequency": "high",
      "context": "遊技場で提供される報酬",
      "must_not_decompose": true
    },
    {
      "id": 10,
      "word": "景品規制",
      "category": "law_concepts",
      "importance": 4,
      "frequency": "high",
      "context": "景品の種類・金額の規制",
      "must_not_decompose": true
    },
    {
      "id": 11,
      "word": "景品交換",
      "category": "law_concepts",
      "importance": 3,
      "frequency": "medium",
      "context": "遊技球などを景品に交換する行為",
      "must_not_decompose": true
    },
    {
      "id": 12,
      "word": "営業時間",
      "category": "law_concepts",
      "importance": 4,
      "frequency": "high",
      "context": "遊技場が営業できる時間帯",
      "must_not_decompose": true
    },
    {
      "id": 13,
      "word": "不正行為",
      "category": "law_concepts",
      "importance": 5,
      "frequency": "very_high",
      "context": "法令に違反する不当な行為",
      "must_not_decompose": true
    },
    {
      "id": 14,
      "word": "取消",
      "category": "law_process",
      "importance": 4,
      "frequency": "high",
      "context": "営業許可などの取り消し",
      "must_not_decompose": false
    },
    {
      "id": 15,
      "word": "取消し要件",
      "category": "law_concepts",
      "importance": 4,
      "frequency": "high",
      "context": "営業許可が取り消される条件",
      "must_not_decompose": true
    },
    {
      "id": 16,
      "word": "失効",
      "category": "law_process",
      "importance": 3,
      "frequency": "medium",
      "context": "許可などの効力が失われること",
      "must_not_decompose": false
    },
    {
      "id": 17,
      "word": "申請",
      "category": "law_process",
      "importance": 4,
      "frequency": "high",
      "context": "行政機関へ申し出ること",
      "must_not_decompose": false
    },
    {
      "id": 18,
      "word": "申請手続き",
      "category": "law_concepts",
      "importance": 3,
      "frequency": "medium",
      "context": "申請に必要な一連の手続き",
      "must_not_decompose": true
    },
    {
      "id": 19,
      "word": "申請書",
      "category": "documents",
      "importance": 3,
      "frequency": "medium",
      "context": "行政機関に提出する申請文書",
      "must_not_decompose": true
    },
    {
      "id": 20,
      "word": "公安委員会",
      "category": "authority",
      "importance": 4,
      "frequency": "high",
      "context": "都道府県の風営法を執行する機関",
      "must_not_decompose": true
    },
    {
      "id": 21,
      "word": "都道府県",
      "category": "jurisdiction",
      "importance": 3,
      "frequency": "medium",
      "context": "日本の地方行政単位",
      "must_not_decompose": true
    },
    {
      "id": 22,
      "word": "主基板",
      "category": "equipment",
      "importance": 4,
      "frequency": "high",
      "context": "遊技機の中枢的な基板",
      "must_not_decompose": true
    },
    {
      "id": 23,
      "word": "外部端子",
      "category": "equipment",
      "importance": 3,
      "frequency": "medium",
      "context": "遊技機の外部との接続端子",
      "must_not_decompose": true
    },
    {
      "id": 24,
      "word": "基板ケース",
      "category": "equipment",
      "importance": 3,
      "frequency": "medium",
      "context": "基板を収納する筐体",
      "must_not_decompose": true
    },
    {
      "id": 25,
      "word": "かしめ",
      "category": "security_measure",
      "importance": 3,
      "frequency": "medium",
      "context": "基板ケースをとめる製造工程",
      "must_not_decompose": false
    },
    {
      "id": 26,
      "word": "セキュリティ",
      "category": "concepts",
      "importance": 3,
      "frequency": "medium",
      "context": "不正防止のための安全対策",
      "must_not_decompose": false
    },
    {
      "id": 27,
      "word": "中古遊技機",
      "category": "equipment",
      "importance": 3,
      "frequency": "medium",
      "context": "以前使用された遊技機",
      "must_not_decompose": true
    },
    {
      "id": 28,
      "word": "リサイクル",
      "category": "law_concepts",
      "importance": 3,
      "frequency": "medium",
      "context": "廃棄物の再利用・再処理",
      "must_not_decompose": false
    },
    {
      "id": 29,
      "word": "廃棄物",
      "category": "concepts",
      "importance": 2,
      "frequency": "low",
      "context": "使用済み遊技機などの不要物",
      "must_not_decompose": true
    },
    {
      "id": 30,
      "word": "製造業者",
      "category": "actor",
      "importance": 3,
      "frequency": "medium",
      "context": "遊技機を製造する企業",
      "must_not_decompose": true
    },
    {
      "id": 31,
      "word": "販売業者",
      "category": "actor",
      "importance": 3,
      "frequency": "medium",
      "context": "遊技機を販売する企業",
      "must_not_decompose": true
    },
    {
      "id": 32,
      "word": "設置",
      "category": "actions",
      "importance": 3,
      "frequency": "medium",
      "context": "遊技機を営業所に配置すること",
      "must_not_decompose": false
    },
    {
      "id": 33,
      "word": "新台設置",
      "category": "law_concepts",
      "importance": 3,
      "frequency": "medium",
      "context": "新しい遊技機を営業所に設置すること",
      "must_not_decompose": true
    },
    {
      "id": 34,
      "word": "点検",
      "category": "actions",
      "importance": 3,
      "frequency": "medium",
      "context": "遊技機の動作・状態を確認すること",
      "must_not_decompose": false
    },
    {
      "id": 35,
      "word": "点検確認",
      "category": "law_concepts",
      "importance": 3,
      "frequency": "medium",
      "context": "遊技機の点検後の確認作業",
      "must_not_decompose": true
    },
    {
      "id": 36,
      "word": "保守管理",
      "category": "law_concepts",
      "importance": 3,
      "frequency": "medium",
      "context": "遊技機を適切に維持管理すること",
      "must_not_decompose": true
    },
    {
      "id": 37,
      "word": "製造番号",
      "category": "identification",
      "importance": 3,
      "frequency": "medium",
      "context": "遊技機を識別するための番号",
      "must_not_decompose": true
    },
    {
      "id": 38,
      "word": "立入検査",
      "category": "law_process",
      "importance": 3,
      "frequency": "medium",
      "context": "公安委員会が営業所に立ち入り検査すること",
      "must_not_decompose": true
    },
    {
      "id": 39,
      "word": "行政処分",
      "category": "law_process",
      "importance": 4,
      "frequency": "high",
      "context": "行政機関が下す処分（営業停止など）",
      "must_not_decompose": true
    },
    {
      "id": 40,
      "word": "罰則",
      "category": "law_concepts",
      "importance": 4,
      "frequency": "high",
      "context": "違反者に科せられる懲役・罰金",
      "must_not_decompose": false
    },
    {
      "id": 41,
      "word": "違反",
      "category": "law_concepts",
      "importance": 4,
      "frequency": "high",
      "context": "法令に違反する行為",
      "must_not_decompose": false
    },
    {
      "id": 42,
      "word": "チップ",
      "category": "equipment",
      "importance": 2,
      "frequency": "low",
      "context": "遊技機内のセキュリティ用IC",
      "must_not_decompose": false
    },
    {
      "id": 43,
      "word": "有効期間",
      "category": "concepts",
      "importance": 3,
      "frequency": "medium",
      "context": "営業許可や型式検定の効力期間",
      "must_not_decompose": true
    },
    {
      "id": 44,
      "word": "無期限有効",
      "category": "law_concepts",
      "importance": 3,
      "frequency": "medium",
      "context": "営業許可が有効期限なく続くこと",
      "must_not_decompose": true
    },
    {
      "id": 45,
      "word": "3年有効",
      "category": "law_concepts",
      "importance": 3,
      "frequency": "medium",
      "context": "型式検定が3年間有効であること",
      "must_not_decompose": true
    },
    {
      "id": 46,
      "word": "リサイクル推進法",
      "category": "law_concepts",
      "importance": 2,
      "frequency": "low",
      "context": "資源有効利用促進法（改正リサイクル法）",
      "must_not_decompose": true
    }
  ]
}
